[
  {
    "header": {
      "name": "WL_RAW_PROD_CAL-CCL-FLOW-GR_2009-03-09_50",
      "well": "15/9-F-14",
      "operator": "StatoilHydro",
      "serviceCompany": "Schlumberger",
      "country": "Norway",
      "field": "Volve",
      "date": "2009-03-08T23:00:00Z",
      "source": "Converted from DLIS by Log Studio 4.87 - Petroware AS",
      "startIndex": 1866630.5,
      "endIndex": 2190630.5,
      "step": 1000.0
    },
    "curves": [
      {
        "name": "TIME",
        "description": "1 second River Time",
        "quantity": null,
        "unit": "ms",
        "valueType": "float",
        "dimensions": 1
      },
      {
        "name": "TDEP",
        "description": "1 second River Depth",
        "quantity": null,
        "unit": "0.1 in",
        "valueType": "float",
        "dimensions": 1
      },
      {
        "name": "TENS_SL",
        "description": "Cable Tension",
        "quantity": null,
        "unit": "lbf",
        "valueType": "float",
        "dimensions": 1
      },
      {
        "name": "DEPT_SL",
        "description": "Station logging depth",
        "quantity": null,
        "unit": "0.1 in",
        "valueType": "float",
        "dimensions": 1
      },
      {
        "name": "ETIM_PL",
        "description": "Elapsed Logging Time",
        "quantity": null,
        "unit": "s",
        "valueType": "float",
        "dimensions": 1
      },
      {
        "name": "TOJ",
        "description": "Time of Job",
        "quantity": null,
        "unit": "s",
        "valueType": "float",
        "dimensions": 1
      },
      {
        "name": "RSPI_SL",
        "description": "Raw Main Spinner Velocity",
        "quantity": null,
        "unit": "c/s",
        "valueType": "float",
        "dimensions": 1
      },
      {
        "name": "SPIN_SL",
        "description": "Main Spinner Velocity",
        "quantity": null,
        "unit": "c/s",
        "valueType": "float",
        "dimensions": 1
      },
      {
        "name": "RSP1_SL",
        "description": "Raw Auxiliary Spinner 1 Velocity",
        "quantity": null,
        "unit": "c/s",
        "valueType": "float",
        "dimensions": 1
      },
      {
        "name": "SPI1_SL",
        "description": "Auxiliary Spinner 1 Velocity",
        "quantity": null,
        "unit": "c/s",
        "valueType": "float",
        "dimensions": 1
      },
      {
        "name": "PFC1_SL",
        "description": "PFCS CaliperX (station)",
        "quantity": null,
        "unit": "in",
        "valueType": "float",
        "dimensions": 1
      },
      {
        "name": "PFC2_SL",
        "description": "PFCS CaliperY (station)",
        "quantity": null,
        "unit": "in",
        "valueType": "float",
        "dimensions": 1
      },
      {
        "name": "DFRB_SL",
        "description": "Calibrated Relative Bearing",
        "quantity": null,
        "unit": "deg",
        "valueType": "float",
        "dimensions": 1
      },
      {
        "name": "RGR_SL",
        "description": "Raw Gamma Ray",
        "quantity": null,
        "unit": "gAPI",
        "valueType": "float",
        "dimensions": 1
      },
      {
        "name": "GR_SL",
        "description": "Gamma Ray",
        "quantity": null,
        "unit": "gAPI",
        "valueType": "float",
        "dimensions": 1
      },
      {
        "name": "WTEP_SL",
        "description": "Well Temperature",
        "quantity": null,
        "unit": "degC",
        "valueType": "float",
        "dimensions": 1
      },
      {
        "name": "QGPF_SL",
        "description": "PBMS CQG Pressure Ref.Beat",
        "quantity": null,
        "unit": "Hz",
        "valueType": "float",
        "dimensions": 1
      },
      {
        "name": "QGTF_SL",
        "description": "PBMS CQG Temperature Ref.Beat",
        "quantity": null,
        "unit": "Hz",
        "valueType": "float",
        "dimensions": 1
      },
      {
        "name": "QGKTF_SL",
        "description": "PBMS CQG Clock Temp. Ref.Beat",
        "quantity": null,
        "unit": "Hz",
        "valueType": "float",
        "dimensions": 1
      },
      {
        "name": "QGKF_SL",
        "description": "PBMS CQG Clock Freq Ref.Beat",
        "quantity": null,
        "unit": "Hz",
        "valueType": "float",
        "dimensions": 1
      },
      {
        "name": "WTPE_SL",
        "description": "PBMS Well Temp Period",
        "quantity": null,
        "unit": "ms",
        "valueType": "float",
        "dimensions": 1
      },
      {
        "name": "MTEP_SL",
        "description": "Manometer Temperature",
        "quantity": null,
        "unit": "degC",
        "valueType": "float",
        "dimensions": 1
      },
      {
        "name": "TOD7",
        "description": "Time of Day",
        "quantity": null,
        "unit": "s",
        "valueType": "integer",
        "dimensions": 1
      },
      {
        "name": "RCVL_SL",
        "description": "Raw Main Cable Velocity",
        "quantity": null,
        "unit": "m/min",
        "valueType": "float",
        "dimensions": 1
      },
      {
        "name": "SCVL_SL",
        "description": "Main Cable Velocity",
        "quantity": null,
        "unit": "m/min",
        "valueType": "float",
        "dimensions": 1
      },
      {
        "name": "RCV1_SL",
        "description": "Raw Auxiliary Cable 1 Velocity",
        "quantity": null,
        "unit": "m/min",
        "valueType": "float",
        "dimensions": 1
      },
      {
        "name": "SCV1_SL",
        "description": "Auxiliary Cable 1 Velocity",
        "quantity": null,
        "unit": "m/min",
        "valueType": "float",
        "dimensions": 1
      },
      {
        "name": "WPRE_SL",
        "description": "Well Pressure",
        "quantity": null,
        "unit": "bar",
        "valueType": "float",
        "dimensions": 1
      },
      {
        "name": "QGCP_SL",
        "description": "PBMS CQG Compensated Pressure",
        "quantity": null,
        "unit": "kPa",
        "valueType": "float",
        "dimensions": 1
      }
    ],
    "data": [
      [1866630.5, 1249226, 3115, 1249226,   0, 293318, 7.47000, 7.37320, 5.28229, 6.02227, 6.9, 6.21119, 11.288,  3.6947,  5.0020, 107.505, 13687.6, 428122, 485141, 14622.9, 4.12527, 107.7, 1236760118, 0, 0, 0, 0, 297.365, 29736.5],
      [1867630.5, 1249226, 3116, 1249226,   1, 293319, 7.11429, 7.36682, 5.28229, 6.06119, 6.9, 6.21392, 11.288,  6.1601,  7.6598, 107.505, 13687.6, 428122, 485141, 14622.9, 4.12527, 107.7, 1236760119, 0, 0, 0, 0, 297.364, 29736.4],
      [1868630.5, 1249226, 3116, 1249226,   2, 293320, 7.22100, 7.35405, 8.07970, 6.11670, 6.9, 6.21374, 11.288,  7.7656,  9.1632, 107.506, 13687.6, 428122, 485141, 14622.9, 4.12528, 107.7, 1236760120, 0, 0, 0, 0, 297.363, 29736.3],
      [1869630.5, 1249226, 3115, 1249226,   3, 293321, 7.31437, 7.33490, 8.07970, 6.32138, 6.9, 6.21835, 11.288, 16.9841, 11.3579, 107.506, 13687.6, 428123, 485141, 14622.9, 4.12528, 107.7, 1236760121, 0, 0, 0, 0, 297.362, 29736.2],
      [1870630.5, 1249226, 3115, 1249226,   4, 293322, 7.38700, 7.32213, 8.07970, 6.53410, 6.9, 6.21628, 11.288, 11.2114, 13.0581, 107.505, 13687.6, 428123, 485141, 14623.0, 4.12527, 107.7, 1236760122, 0, 0, 0, 0, 297.360, 29736.0],
      [1871630.5, 1249226, 3115, 1249226,   5, 293323, 7.22100, 7.30297, 6.00403, 6.74682, 6.9, 6.21374, 11.288, 14.6684, 13.9197, 107.502, 13687.5, 428123, 485141, 14623.0, 4.12524, 107.7, 1236760123, 0, 0, 0, 0, 297.358, 29735.8],
      [1872630.5, 1249226, 3114, 1249226,   6, 293324, 7.30400, 7.29021, 5.78814, 6.95149, 6.9, 6.21374, 11.288, 14.6610, 12.4212, 107.502, 13687.5, 428123, 485141, 14623.0, 4.12525, 107.7, 1236760124, 0, 0, 0, 0, 297.357, 29735.7],
      [1873630.5, 1249226, 3115, 1249226,   7, 293325, 7.38700, 7.29021, 5.78814, 7.01288, 6.9, 6.21374, 11.288, 12.0738, 13.9735, 107.503, 13687.5, 428123, 485141, 14623.0, 4.12525, 107.7, 1236760125, 0, 0, 0, 0, 297.355, 29735.5],
      [1874630.5, 1249226, 3115, 1249226,   8, 293326, 7.30400, 7.31757, 6.00403, 7.07426, 6.9, 6.21119, 11.288,  9.4913, 13.1107, 107.503, 13687.5, 428123, 485141, 14623.0, 4.12525, 107.7, 1236760126, 0, 0, 0, 0, 297.353, 29735.3],
      [1875630.5, 1249226, 3115, 1249226,   9, 293327, 7.22100, 7.33672, 7.94302, 6.92046, 6.9, 6.21882, 11.288, 18.9731, 12.9382, 107.504, 13687.4, 428123, 485141, 14623.0, 4.12526, 107.7, 1236760127, 0, 0, 0, 0, 297.351, 29735.1],
      [1876630.5, 1249226, 3115, 1249226,  10, 293328, 7.30400, 7.32475, 8.04769, 6.80129, 6.9, 6.21119, 11.288, 10.3541, 13.4571, 107.502, 13687.4, 428123, 485141, 14623.0, 4.12524, 107.7, 1236760128, 0, 0, 0, 0, 297.351, 29735.1],
      [1877630.5, 1249226, 3114, 1249226,  11, 293329, 7.22100, 7.31198, 8.04769, 6.71905, 6.9, 6.21882, 11.288, 13.7986, 14.4910, 107.502, 13687.4, 428123, 485141, 14623.0, 4.12524, 107.7, 1236760129, 0, 0, 0, 0, 297.351, 29735.1],
      [1878630.5, 1249226, 3111, 1249226,  12, 293330, 7.30400, 7.33114, 7.94302, 6.79712, 6.9, 6.21882, 11.288, 14.6684, 14.1478, 107.501, 13687.4, 428123, 485142, 14623.0, 4.12524, 107.7, 1236760130, 0, 0, 0, 0, 297.349, 29734.9],
      [1879630.5, 1249226, 3113, 1249226,  13, 293331, 7.47000, 7.33752, 6.08027, 6.89180, 6.9, 6.21374, 11.288, 14.6610, 13.9743, 107.502, 13687.4, 428123, 485142, 14623.0, 4.12524, 107.7, 1236760131, 0, 0, 0, 0, 297.346, 29734.6],
      [1880630.5, 1249226, 3114, 1249226,  14, 293332, 7.47000, 7.33752, 6.08027, 6.94890, 6.9, 6.21882, 11.288, 17.2569, 12.9939, 107.502, 13687.3, 428123, 485142, 14623.0, 4.12524, 107.7, 1236760132, 0, 0, 0, 0, 297.344, 29734.4],
      [1881630.5, 1249226, 3113, 1249226,  15, 293333, 7.47000, 7.33752, 6.08027, 6.91185, 6.9, 6.21628, 11.288,  9.4865, 12.3024, 107.503, 13687.3, 428123, 485142, 14623.0, 4.12525, 107.7, 1236760133, 0, 0, 0, 0, 297.344, 29734.4],
      [1882630.5, 1249226, 3113, 1249226,  16, 293334, 7.15875, 7.35029, 6.53050, 6.67516, 6.9, 6.21835, 11.288,  8.8964, 12.1314, 107.503, 13687.3, 428123, 485142, 14623.0, 4.12525, 107.7, 1236760134, 0, 0, 0, 0, 297.343, 29734.3],
      [1883630.5, 1249226, 3114, 1249226,  17, 293335, 7.22100, 7.35667, 7.01051, 6.43041, 6.9, 6.21119, 11.288, 11.2114, 10.4039, 107.502, 13687.3, 428123, 485142, 14623.0, 4.12524, 107.7, 1236760135, 0, 0, 0, 0, 297.341, 29734.1],
      [1884630.5, 1249226, 3113, 1249226,  18, 293336, 7.47000, 7.37583, 7.01896, 6.18567, 6.9, 6.21628, 11.288, 13.8055, 10.9238, 107.502, 13687.3, 428123, 485142, 14623.0, 4.12524, 107.7, 1236760136, 0, 0, 0, 0, 297.339, 29733.9],
      [1885630.5, 1249226, 3114, 1249226,  19, 293337, 7.38700, 7.38221, 7.01896, 5.94897, 6.9, 6.21882, 11.288,  8.6198, 12.5942, 107.500, 13687.3, 428123, 485142, 14623.0, 4.12523, 107.7, 1236760137, 0, 0, 0, 0, 297.339, 29733.9],
      [1886630.5, 1249226, 3113, 1249226,  20, 293338, 7.38700, 7.38860, 6.53050, 5.90655, 6.9, 6.21374, 11.288, 12.0859, 12.2502, 107.500, 13687.2, 428123, 485142, 14623.0, 4.12523, 107.7, 1236760138, 0, 0, 0, 0, 297.336, 29733.6],
      [1887630.5, 1249226, 3113, 1249226,  21, 293339, 7.30400, 7.40137, 5.52235, 5.87307, 6.9, 6.22391, 11.288, 17.2482, 11.2139, 107.501, 13687.2, 428123, 485142, 14623.0, 4.12523, 107.7, 1236760139, 0, 0, 0, 0, 297.335, 29733.5],
      [1888630.5, 1249226, 3111, 1249226,  22, 293340, 7.38700, 7.39498, 4.86602, 5.83065, 6.9, 6.21119, 11.288,  9.4913, 11.3872, 107.501, 13687.2, 428123, 485142, 14623.0, 4.12523, 107.7, 1236760140, 0, 0, 0, 0, 297.334, 29733.4],
      [1889630.5, 1249226, 3111, 1249226,  23, 293341, 7.38700, 7.41294, 4.86602, 5.75359, 6.9, 6.21628, 11.288,  8.6241, 11.2134, 107.499, 13687.2, 428123, 485142, 14623.0, 4.12522, 107.7, 1236760141, 0, 0, 0, 0, 297.335, 29733.5],
      [1890630.5, 1249226, 3114, 1249226,  24, 293342, 7.47000, 7.43848, 4.86602, 5.76032, 6.9, 6.21628, 11.288,  9.4865,  9.8346, 107.500, 13687.2, 428123, 485142, 14623.0, 4.12522, 107.7, 1236760142, 0, 0, 0, 0, 297.335, 29733.4],
      [1891630.5, 1249226, 3113, 1249226,  25, 293343, 7.38700, 7.45125, 4.86602, 5.76641, 6.9, 6.21374, 11.288, 11.2170, 10.5236, 107.500, 13687.2, 428123, 485142, 14623.0, 4.12523, 107.7, 1236760143, 0, 0, 0, 0, 297.332, 29733.2],
      [1892630.5, 1249226, 3111, 1249226,  26, 293344, 7.55300, 7.46402, 5.52879, 5.76077, 6.9, 6.21374, 11.288, 10.3541, 10.5245, 107.498, 13687.1, 428123, 485142, 14623.0, 4.12521, 107.7, 1236760144, 0, 0, 0, 0, 297.329, 29732.9],
      [1893630.5, 1249226, 3113, 1249226,  27, 293345, 7.63600, 7.47040, 5.64501, 5.80442, 6.9, 6.21119, 11.288, 12.9362,  9.7589, 107.499, 13687.1, 428123, 485142, 14623.0, 4.12521, 107.7, 1236760145, 0, 0, 0, 0, 297.328, 29732.8],
      [1894630.5, 1249226, 3113, 1249226,  28, 293346, 7.38700, 7.47678, 5.52879, 5.93710, 6.9, 6.21119, 11.288,  8.6285,  9.7589, 107.500, 13687.1, 428123, 485142, 14623.0, 4.12522, 107.7, 1236760146, 0, 0, 0, 0, 297.328, 29732.8],
      [1895630.5, 1249226, 3111, 1249226,  29, 293347, 7.39219, 7.48955, 5.52879, 6.09707, 6.9, 6.21596, 11.288,  5.6587,  9.9303, 107.499, 13687.1, 428123, 485142, 14623.0, 4.12522, 107.7, 1236760147, 0, 0, 0, 0, 297.329, 29732.9],
      [1896630.5, 1249226, 3111, 1249226,  30, 293348, 7.55300, 7.50871, 7.09801, 6.25705, 6.9, 6.21119, 11.288, 11.2170, 10.6219, 107.498, 13687.1, 428123, 485142, 14623.0, 4.12520, 107.7, 1236760148, 0, 0, 0, 0, 297.328, 29732.8],
      [1897630.5, 1249226, 3113, 1249226,  31, 293349, 7.63600, 7.51509, 7.09801, 6.44021, 6.9, 6.21628, 11.288, 11.2114, 11.4835, 107.499, 13687.1, 428123, 485142, 14623.0, 4.12522, 107.7, 1236760149, 0, 0, 0, 0, 297.327, 29732.7],
      [1898630.5, 1249226, 3111, 1249226,  32, 293350, 7.55300, 7.52786, 6.94568, 6.60590, 6.9, 6.21882, 11.288, 16.3941, 12.7677, 107.498, 13687.1, 428123, 485142, 14623.0, 4.12521, 107.7, 1236760150, 0, 0, 0, 0, 297.325, 29732.5],
      [1899630.5, 1249226, 3111, 1249226,  33, 293351, 7.47000, 7.51509, 7.09801, 6.72062, 6.9, 6.21119, 11.288, 12.9362, 13.1115, 107.496, 13687.0, 428124, 485142, 14623.0, 4.12519, 107.7, 1236760151, 0, 0, 0, 0, 297.324, 29732.4],
      [1900630.5, 1249226, 3110, 1249226,  34, 293352, 7.38700, 7.49594, 7.24713, 6.89639, 6.9, 6.21119, 11.288, 12.0798, 13.6304, 107.497, 13687.0, 428124, 485142, 14623.0, 4.12520, 107.7, 1236760152, 0, 0, 0, 0, 297.323, 29732.3],
      [1901630.5, 1249226, 3113, 1249226,  35, 293353, 7.55300, 7.49035, 6.94568, 7.08110, 6.9, 6.21119, 11.288, 12.9362, 11.3864, 107.497, 13687.0, 428124, 485142, 14623.0, 4.12520, 107.7, 1236760153, 0, 0, 0, 0, 297.322, 29732.2],
      [1902630.5, 1249226, 3111, 1249226,  36, 293354, 7.63600, 7.50272, 6.94568, 7.24734, 6.9, 6.21119, 11.288, 13.8055, 11.2152, 107.497, 13687.0, 428124, 485142, 14623.0, 4.12520, 107.7, 1236760154, 0, 0, 0, 0, 297.322, 29732.2],
      [1903630.5, 1249226, 3111, 1249226,  37, 293355, 7.55300, 7.49634, 7.24713, 7.29287, 6.9, 6.21628, 11.288,  5.1745, 11.0415, 107.497, 13687.0, 428124, 485142, 14623.0, 4.12520, 107.7, 1236760155, 0, 0, 0, 0, 297.321, 29732.1],
      [1904630.5, 1249226, 3110, 1249226,  38, 293356, 7.55300, 7.48357, 7.02004, 7.28428, 6.9, 6.21628, 11.288, 12.0798,  9.8341, 107.497, 13687.0, 428124, 485142, 14623.0, 4.12520, 107.7, 1236760156, 0, 0, 0, 0, 297.320, 29732.0],
      [1905630.5, 1249226, 3111, 1249226,  39, 293357, 7.38700, 7.47718, 7.02004, 7.23263, 6.9, 6.22391, 11.288, 11.2114,  8.5288, 107.496, 13687.0, 428124, 485143, 14623.0, 4.12519, 107.7, 1236760157, 0, 0, 0, 0, 297.319, 29731.9],
      [1906630.5, 1249226, 3111, 1249226,  40, 293358, 7.38700, 7.47718, 7.93004, 7.16926, 6.9, 6.21119, 11.288,  6.8993,  9.9098, 107.494, 13687.0, 428124, 485143, 14623.0, 4.12517, 107.7, 1236760158, 0, 0, 0, 0, 297.319, 29731.9],
      [1907630.5, 1249226, 3110, 1249226,  41, 293359, 7.31437, 7.48357, 7.93004, 7.09442, 6.9, 6.21119, 11.288,  7.2789, 10.2522, 107.495, 13687.0, 428124, 485143, 14623.0, 4.12518, 107.7, 1236760159, 0, 0, 0, 0, 297.317, 29731.7],
      [1908630.5, 1249226, 3111, 1249226,  42, 293360, 7.55300, 7.48357, 7.68987, 7.06539, 6.9, 6.21628, 11.288, 12.0798,  9.5638, 107.495, 13687.0, 428124, 485143, 14623.0, 4.12518, 107.7, 1236760160, 0, 0, 0, 0, 297.317, 29731.7],
      [1909630.5, 1249226, 3110, 1249226,  43, 293361, 7.47000, 7.46441, 7.68987, 7.03637, 6.9, 6.21119, 11.288, 13.7917, 11.2887, 107.494, 13687.0, 428124, 485143, 14623.0, 4.12517, 107.7, 1236760161, 0, 0, 0, 0, 297.317, 29731.7],
      [1910630.5, 1249226, 3110, 1249226,  44, 293362, 7.47000, 7.45803, 6.98640, 7.02322, 6.9, 6.21628, 11.288,  7.7695, 12.9391, 107.495, 13687.0, 428124, 485143, 14623.0, 4.12518, 107.7, 1236760162, 0, 0, 0, 0, 297.317, 29731.7],
      [1911630.5, 1249226, 3110, 1249226,  45, 293363, 7.47000, 7.45164, 6.27422, 7.02636, 6.9, 6.21628, 11.288, 15.5234, 12.4205, 107.492, 13686.9, 428124, 485143, 14623.0, 4.12516, 107.7, 1236760163, 0, 0, 0, 0, 297.316, 29731.6],
      [1912630.5, 1249226, 3111, 1249226,  46, 293364, 7.47000, 7.45803, 6.27422, 7.02949, 6.9, 6.21882, 11.288, 15.5312, 12.4232, 107.493, 13686.9, 428124, 485143, 14623.0, 4.12517, 107.7, 1236760164, 0, 0, 0, 0, 297.314, 29731.4],
      [1913630.5, 1249226, 3111, 1249226,  47, 293365, 7.47000, 7.47080, 6.27422, 6.98828, 6.9, 6.21374, 11.288,  9.4865, 13.4566, 107.493, 13686.9, 428124, 485143, 14623.0, 4.12517, 107.7, 1236760165, 0, 0, 0, 0, 297.313, 29731.3],
      [1914630.5, 1249226, 3110, 1249226,  48, 293366, 7.55300, 7.48277, 6.56834, 6.99678, 6.9, 6.21374, 11.288, 13.8055, 13.6291, 107.494, 13686.9, 428124, 485143, 14623.0, 4.12517, 107.7, 1236760166, 0, 0, 0, 0, 297.314, 29731.4],
      [1915630.5, 1249226, 3110, 1249226,  49, 293367, 7.38700, 7.47000, 6.56834, 7.06609, 6.9, 6.21374, 11.288, 12.9362, 13.9742, 107.494, 13686.9, 428124, 485143, 14623.0, 4.12517, 107.7, 1236760167, 0, 0, 0, 0, 297.312, 29731.2],
      [1916630.5, 1249226, 3111, 1249226,  50, 293368, 7.47000, 7.47000, 7.07626, 7.16565, 6.9, 6.21628, 11.288, 16.3858, 14.6641, 107.493, 13686.9, 428124, 485143, 14623.0, 4.12516, 107.7, 1236760168, 0, 0, 0, 0, 297.312, 29731.2],
      [1917630.5, 1249226, 3111, 1249226,  51, 293369, 7.47000, 7.47639, 7.06077, 7.31932, 6.9, 6.21628, 11.288, 17.2569, 13.6287, 107.492, 13686.9, 428124, 485143, 14623.0, 4.12516, 107.7, 1236760169, 0, 0, 0, 0, 297.311, 29731.1],
      [1918630.5, 1249226, 3111, 1249226,  52, 293370, 7.47000, 7.47000, 7.06077, 7.48764, 6.9, 6.21374, 11.288, 12.9362, 13.6295, 107.493, 13686.8, 428124, 485143, 14623.0, 4.12516, 107.7, 1236760170, 0, 0, 0, 0, 297.309, 29730.9],
      [1919630.5, 1249226, 3110, 1249226,  53, 293371, 7.55300, 7.47639, 7.39428, 7.67743, 6.9, 6.21882, 11.288,  8.6285, 12.4222, 107.492, 13686.9, 428124, 485143, 14623.0, 4.12515, 107.7, 1236760171, 0, 0, 0, 0, 297.310, 29731.0],
      [1920630.5, 1249226, 3111, 1249226,  54, 293372, 7.47000, 7.47639, 8.04061, 7.84575, 6.9, 6.21596, 11.288, 12.9402, 10.3513, 107.492, 13686.9, 428124, 485143, 14623.0, 4.12516, 107.7, 1236760172, 0, 0, 0, 0, 297.310, 29731.0],
      [1921630.5, 1249226, 3111, 1249226,  55, 293373, 7.38700, 7.47639, 8.59090, 7.94269, 6.9, 6.21119, 11.288, 10.3489,  9.4889, 107.492, 13686.8, 428124, 485143, 14623.0, 4.12515, 107.7, 1236760173, 0, 0, 0, 0, 297.309, 29730.9],
      [1922630.5, 1249226, 3110, 1249226,  56, 293374, 7.47000, 7.48277, 8.98413, 7.99778, 6.9, 6.21119, 11.288,  6.9028, 10.8679, 107.492, 13686.8, 428124, 485143, 14623.0, 4.12515, 107.7, 1236760174, 0, 0, 0, 0, 297.309, 29730.9],
      [1923630.5, 1249226, 3111, 1249226,  57, 293375, 7.55300, 7.48277, 8.98413, 8.01381, 6.9, 6.21374, 11.288,  8.6241, 11.5587, 107.492, 13686.8, 428124, 485143, 14623.0, 4.12516, 107.7, 1236760175, 0, 0, 0, 0, 297.308, 29730.8],
      [1924630.5, 1249226, 3110, 1249226,  58, 293376, 7.38700, 7.50192, 8.46237, 8.02431, 6.9, 6.22137, 11.288, 15.5234, 11.5587, 107.492, 13686.8, 428124, 485143, 14623.0, 4.12515, 107.7, 1236760176, 0, 0, 0, 0, 297.307, 29730.7],
      [1925630.5, 1249226, 3110, 1249226,  59, 293377, 7.55300, 7.50831, 8.74153, 8.01548, 6.9, 6.21628, 11.288, 16.3941, 13.4569, 107.491, 13686.8, 428124, 485143, 14623.0, 4.12515, 107.7, 1236760177, 0, 0, 0, 0, 297.308, 29730.8],
      [1926630.5, 1249226, 3111, 1249226,  60, 293378, 7.47000, 7.50192, 8.46237, 7.98099, 6.9, 6.21882, 11.288, 10.3489, 14.1469, 107.492, 13686.8, 428124, 485143, 14623.0, 4.12516, 107.7, 1236760178, 0, 0, 0, 0, 297.307, 29730.7],
      [1927630.5, 1249226, 3111, 1249226,  61, 293379, 7.55300, 7.50791, 7.82846, 7.91612, 6.9, 6.21374, 11.288, 16.3941, 12.5953, 107.491, 13686.8, 428124, 485143, 14623.0, 4.12515, 107.7, 1236760179, 0, 0, 0, 0, 297.307, 29730.7],
      [1928630.5, 1249226, 3108, 1249226,  62, 293380, 7.47000, 7.50791, 7.28462, 7.80892, 6.9, 6.21119, 11.288, 12.0738, 11.5588, 107.490, 13686.8, 428124, 485143, 14623.0, 4.12514, 107.7, 1236760180, 0, 0, 0, 0, 297.306, 29730.6],
      [1929630.5, 1249226, 3110, 1249226,  63, 293381, 7.47000, 7.50152, 7.28462, 7.75031, 6.9, 6.21374, 11.288,  7.7656, 12.5952, 107.490, 13686.8, 428125, 485144, 14623.0, 4.12514, 107.7, 1236760181, 0, 0, 0, 0, 297.305, 29730.5],
      [1930630.5, 1249226, 3110, 1249226,  64, 293382, 7.71900, 7.49514, 7.19729, 7.71101, 6.9, 6.21628, 11.288, 11.2114, 11.9036, 107.490, 13686.8, 428125, 485144, 14623.0, 4.12514, 107.7, 1236760182, 0, 0, 0, 0, 297.305, 29730.5],
      [1931630.5, 1249226, 3111, 1249226,  65, 293383, 7.55300, 7.51429, 6.94593, 7.69254, 6.9, 6.21628, 11.288, 15.5312, 12.5622, 107.489, 13686.8, 428125, 485144, 14623.0, 4.12513, 107.7, 1236760183, 0, 0, 0, 0, 297.306, 29730.6],
      [1932630.5, 1249226, 3110, 1249226,  66, 293384, 7.47000, 7.51429, 6.94593, 7.56446, 6.9, 6.22137, 11.288, 12.9362, 12.7348, 107.489, 13686.8, 428125, 485144, 14623.0, 4.12513, 107.7, 1236760184, 0, 0, 0, 0, 297.304, 29730.4],
      [1933630.5, 1249226, 3111, 1249226,  67, 293385, 7.54781, 7.51429, 7.19729, 7.53910, 6.9, 6.21596, 11.288, 15.3665, 13.0797, 107.490, 13686.8, 428125, 485144, 14623.0, 4.12514, 107.7, 1236760185, 0, 0, 0, 0, 297.304, 29730.4],
      [1934630.5, 1249226, 3110, 1249226,  68, 293386, 7.38700, 7.51429, 7.19729, 7.56250, 6.9, 6.21374, 11.288,  8.6285, 12.7332, 107.489, 13686.8, 428125, 485144, 14623.0, 4.12513, 107.7, 1236760186, 0, 0, 0, 0, 297.303, 29730.3],
      [1935630.5, 1249226, 3108, 1249226,  69, 293387, 7.38700, 7.52068, 8.22220, 7.60410, 6.9, 6.21374, 11.288, 12.9362, 12.3894, 107.489, 13686.7, 428125, 485144, 14623.0, 4.12513, 107.7, 1236760187, 0, 0, 0, 0, 297.302, 29730.2],
      [1936630.5, 1249226, 3108, 1249226,  70, 293388, 7.47000, 7.53345, 8.47329, 7.64571, 6.9, 6.21882, 11.288, 13.7986, 13.1107, 107.488, 13686.7, 428125, 485144, 14623.0, 4.12512, 107.7, 1236760188, 0, 0, 0, 0, 297.301, 29730.1],
      [1937630.5, 1249226, 3110, 1249226,  71, 293389, 7.63600, 7.50791, 8.22220, 7.69403, 6.9, 6.21119, 11.288, 11.2170, 15.0089, 107.488, 13686.7, 428125, 485144, 14623.0, 4.12512, 107.7, 1236760189, 0, 0, 0, 0, 297.300, 29730.0],
      [1938630.5, 1249226, 3110, 1249226,  72, 293390, 7.55300, 7.50152, 7.07653, 7.76054, 6.9, 6.21628, 11.288, 18.9731, 15.3539, 107.488, 13686.7, 428125, 485144, 14623.0, 4.12512, 107.7, 1236760190, 0, 0, 0, 0, 297.299, 29729.9],
      [1939630.5, 1249226, 3110, 1249226,  73, 293391, 7.47000, 7.50152, 8.13267, 7.81385, 6.9, 6.21628, 11.288, 18.1198, 15.0101, 107.488, 13686.7, 428125, 485144, 14623.0, 4.12512, 107.7, 1236760191, 0, 0, 0, 0, 297.299, 29730.0],
      [1940630.5, 1249226, 3110, 1249226,  74, 293392, 7.55300, 7.50192, 8.13267, 7.77910, 6.9, 6.21374, 11.288, 14.6610, 15.0090, 107.489, 13686.7, 428125, 485144, 14623.0, 4.12513, 107.7, 1236760192, 0, 0, 0, 0, 297.300, 29730.0],
      [1941630.5, 1249226, 3108, 1249226,  75, 293393, 7.55300, 7.50831, 7.82546, 7.73893, 6.9, 6.21882, 11.288, 12.0798, 13.2852, 107.488, 13686.7, 428125, 485144, 14623.0, 4.12512, 107.7, 1236760193, 0, 0, 0, 0, 297.299, 29729.9],
      [1942630.5, 1249226, 3110, 1249226,  76, 293394, 7.63600, 7.52108, 7.82546, 7.61991, 6.9, 6.21119, 11.288, 11.2114, 12.5935, 107.488, 13686.7, 428125, 485144, 14623.0, 4.12512, 107.7, 1236760194, 0, 0, 0, 0, 297.298, 29729.8],
      [1943630.5, 1249226, 3110, 1249226,  77, 293395, 7.38700, 7.52108, 7.82546, 7.48158, 6.9, 6.22137, 11.288, 10.3541, 12.2493, 107.487, 13686.7, 428125, 485144, 14623.0, 4.12512, 107.7, 1236760195, 0, 0, 0, 0, 297.298, 29729.8],
      [1944630.5, 1249226, 3108, 1249226,  78, 293396, 7.47000, 7.50831, 7.81063, 7.41903, 6.9, 6.21882, 11.288, 14.6610, 12.7656, 107.489, 13686.7, 428125, 485144, 14623.0, 4.12513, 107.7, 1236760196, 0, 0, 0, 0, 297.297, 29729.7],
      [1945630.5, 1249226, 3110, 1249226,  79, 293397, 7.47000, 7.50831, 7.63887, 7.45195, 6.9, 6.21596, 11.288, 12.9402, 12.5941, 107.488, 13686.7, 428125, 485144, 14623.0, 4.12512, 107.7, 1236760197, 0, 0, 0, 0, 297.297, 29729.7],
      [1946630.5, 1249226, 3108, 1249226,  80, 293398, 7.55300, 7.50831, 6.74565, 7.40362, 6.9, 6.21374, 11.288, 14.6610, 12.7656, 107.485, 13686.7, 428125, 485144, 14623.0, 4.12510, 107.7, 1236760198, 0, 0, 0, 0, 297.297, 29729.7],
      [1947630.5, 1249226, 3106, 1249226,  81, 293399, 7.47000, 7.48915, 6.67498, 7.40101, 6.9, 6.22137, 11.288, 10.3541, 12.7670, 107.487, 13686.7, 428125, 485144, 14623.0, 4.12511, 107.7, 1236760199, 0, 0, 0, 0, 297.296, 29729.6],
      [1948630.5, 1249226, 3106, 1249226,  82, 293400, 7.55300, 7.48915, 6.67498, 7.42203, 6.9, 6.21628, 11.288, 11.2114, 12.9387, 107.487, 13686.6, 428125, 485144, 14623.0, 4.12511, 107.7, 1236760200, 0, 0, 0, 0, 297.295, 29729.5],
      [1949630.5, 1249226, 3106, 1249226,  83, 293401, 7.47000, 7.48277, 6.67498, 7.42207, 6.9, 6.21882, 11.288, 14.6684, 12.4225, 107.487, 13686.6, 428125, 485144, 14623.0, 4.12511, 107.7, 1236760201, 0, 0, 0, 0, 297.295, 29729.5],
      [1950630.5, 1249226, 3107, 1249226,  84, 293402, 7.47000, 7.48277, 7.40914, 7.42210, 6.9, 6.21628, 11.288, 13.7986, 12.9389, 107.487, 13686.7, 428125, 485144, 14623.0, 4.12511, 107.7, 1236760202, 0, 0, 0, 0, 297.296, 29729.6],
      [1951630.5, 1249226, 3107, 1249226,  85, 293403, 7.55300, 7.48915, 7.50437, 7.42327, 6.9, 6.22391, 11.288, 12.0798, 13.6303, 107.486, 13686.7, 428125, 485144, 14623.0, 4.12510, 107.7, 1236760203, 0, 0, 0, 0, 297.296, 29729.6],
      [1952630.5, 1249226, 3105, 1249226,  86, 293404, 7.47000, 7.49514, 7.50437, 7.34049, 6.9, 6.21374, 11.288, 12.9362, 12.4214, 107.487, 13686.7, 428125, 485144, 14623.0, 4.12511, 107.7, 1236760204, 0, 0, 0, 0, 297.296, 29729.6],
      [1953630.5, 1249226, 3106, 1249226,  87, 293405, 7.30400, 7.50152, 8.09877, 7.42359, 6.9, 6.21374, 11.288, 14.6684, 12.2502, 107.487, 13686.6, 428125, 485144, 14623.0, 4.12511, 107.7, 1236760205, 0, 0, 0, 0, 297.294, 29729.4],
      [1954630.5, 1249226, 3106, 1249226,  88, 293406, 7.55300, 7.52068, 8.09877, 7.48035, 6.9, 6.21374, 11.288,  8.6241, 12.2490, 107.486, 13686.6, 428125, 485144, 14623.0, 4.12510, 107.7, 1236760206, 0, 0, 0, 0, 297.293, 29729.3],
      [1955630.5, 1249226, 3105, 1249226,  89, 293407, 7.55300, 7.52706, 7.82590, 7.53711, 6.9, 6.22137, 11.288, 12.9427, 11.5591, 107.487, 13686.6, 428125, 485144, 14623.0, 4.12511, 107.7, 1236760207, 0, 0, 0, 0, 297.293, 29729.3],
      [1956630.5, 1249226, 3107, 1249226,  90, 293408, 7.38700, 7.52706, 7.82590, 7.67098, 6.9, 6.21882, 11.288, 12.0738, 11.2135, 107.485, 13686.6, 428126, 485144, 14623.0, 4.12509, 107.7, 1236760208, 0, 0, 0, 0, 297.294, 29729.4],
      [1957630.5, 1249226, 3107, 1249226,  91, 293409, 7.55300, 7.53345, 7.82590, 7.74837, 6.9, 6.22137, 11.288,  9.4865, 11.3869, 107.484, 13686.6, 428126, 485145, 14623.0, 4.12508, 107.7, 1236760209, 0, 0, 0, 0, 297.293, 29729.3],
      [1958630.5, 1249226, 3106, 1249226,  92, 293410, 7.54781, 7.53345, 6.56270, 7.87992, 6.9, 6.21358, 11.288, 12.9402, 12.0755, 107.485, 13686.6, 428126, 485145, 14623.0, 4.12509, 107.7, 1236760210, 0, 0, 0, 0, 297.293, 29729.3],
      [1959630.5, 1249226, 3106, 1249226,  93, 293411, 7.63600, 7.55260, 7.82590, 8.01147, 6.9, 6.21374, 11.288,  9.4913, 12.0767, 107.485, 13686.6, 428126, 485145, 14623.0, 4.12509, 107.7, 1236760211, 0, 0, 0, 0, 297.292, 29729.2],
      [1960630.5, 1249226, 3107, 1249226,  94, 293412, 7.71900, 7.56537, 7.41286, 7.95724, 6.9, 6.21628, 11.288, 16.3858, 12.4217, 107.483, 13686.6, 428126, 485145, 14623.0, 4.12507, 107.7, 1236760212, 0, 0, 0, 0, 297.292, 29729.2],
      [1961630.5, 1249226, 3106, 1249226,  95, 293413, 7.63600, 7.57176, 7.41286, 7.90301, 6.9, 6.22137, 11.288, 12.0798, 12.4222, 107.485, 13686.6, 428126, 485145, 14623.0, 4.12510, 107.7, 1236760213, 0, 0, 0, 0, 297.292, 29729.2],
      [1962630.5, 1249226, 3106, 1249226,  96, 293414, 7.47000, 7.57176, 8.41530, 7.84311, 6.9, 6.21374, 11.288, 11.2114, 12.2488, 107.485, 13686.6, 428126, 485145, 14623.0, 4.12510, 107.7, 1236760214, 0, 0, 0, 0, 297.292, 29729.2],
      [1963630.5, 1249226, 3106, 1249226,  97, 293415, 7.55300, 7.58453, 8.41530, 7.74139, 6.9, 6.21374, 11.288, 12.9427, 11.3876, 107.483, 13686.6, 428126, 485145, 14623.0, 4.12508, 107.7, 1236760215, 0, 0, 0, 0, 297.292, 29729.2],
      [1964630.5, 1249226, 3106, 1249226,  98, 293416, 7.55300, 7.57176, 9.21446, 7.68149, 6.9, 6.21628, 11.288,  8.6241, 11.3864, 107.484, 13686.6, 428126, 485145, 14623.0, 4.12508, 107.7, 1236760216, 0, 0, 0, 0, 297.291, 29729.1],
      [1965630.5, 1249226, 3106, 1249226,  99, 293417, 7.71900, 7.57176, 9.21446, 7.71875, 6.9, 6.21882, 11.288, 12.0798, 11.0414, 107.485, 13686.6, 428126, 485145, 14623.0, 4.12509, 107.7, 1236760217, 0, 0, 0, 0, 297.290, 29729.0],
      [1966630.5, 1249226, 3105, 1249226, 100, 293418, 7.47000, 7.57814, 7.39383, 7.65885, 6.9, 6.21374, 11.288, 12.0738, 10.8688, 107.485, 13686.6, 428126, 485145, 14623.0, 4.12509, 107.7, 1236760218, 0, 0, 0, 0, 297.291, 29729.1],
      [1967630.5, 1249226, 3105, 1249226, 101, 293419, 7.63600, 7.57176, 7.39383, 7.67722, 6.9, 6.22137, 11.288,  9.4865, 12.2487, 107.484, 13686.6, 428126, 485145, 14623.0, 4.12509, 107.7, 1236760219, 0, 0, 0, 0, 297.290, 29729.0],
      [1968630.5, 1249226, 3105, 1249226, 102, 293420, 7.55300, 7.57176, 7.04712, 7.69559, 6.9, 6.21882, 11.288, 12.0798, 12.0761, 107.484, 13686.6, 428126, 485145, 14623.0, 4.12509, 107.7, 1236760220, 0, 0, 0, 0, 297.290, 29729.0],
      [1969630.5, 1249226, 3106, 1249226, 103, 293421, 7.55300, 7.59091, 6.50358, 7.62405, 6.9, 6.21628, 11.288, 15.5234, 12.2494, 107.483, 13686.6, 428126, 485145, 14623.0, 4.12507, 107.7, 1236760221, 0, 0, 0, 0, 297.288, 29728.8],
      [1970630.5, 1249226, 3106, 1249226, 104, 293422, 7.38700, 7.58453, 7.04712, 7.56531, 6.9, 6.21374, 11.288, 11.2170, 13.1118, 107.484, 13686.5, 428126, 485145, 14623.0, 4.12509, 107.7, 1236760222, 0, 0, 0, 0, 297.287, 29728.7],
      [1971630.5, 1249226, 3106, 1249226, 105, 293423, 7.54781, 7.57814, 7.04712, 7.44510, 6.9, 6.21835, 11.288, 12.9402, 12.7667, 107.483, 13686.5, 428126, 485145, 14623.0, 4.12508, 107.7, 1236760223, 0, 0, 0, 0, 297.287, 29728.7],
      [1972630.5, 1249226, 3105, 1249226, 106, 293424, 7.71900, 7.55260, 7.04712, 7.38464, 6.9, 6.21374, 11.288, 13.7986, 11.5593, 107.481, 13686.5, 428126, 485145, 14623.0, 4.12506, 107.7, 1236760224, 0, 0, 0, 0, 297.286, 29728.6],
      [1973630.5, 1249226, 3105, 1249226, 107, 293425, 7.63600, 7.54622, 7.65170, 7.46423, 6.9, 6.22137, 11.288, 10.3541, 10.5239, 107.482, 13686.5, 428126, 485145, 14623.0, 4.12507, 107.7, 1236760225, 0, 0, 0, 0, 297.287, 29728.7],
      [1974630.5, 1249226, 3105, 1249226, 108, 293426, 7.63600, 7.52706, 7.65170, 7.54381, 6.9, 6.22391, 11.288,  9.4865,  9.3157, 107.481, 13686.5, 428126, 485145, 14623.0, 4.12506, 107.7, 1236760226, 0, 0, 0, 0, 297.287, 29728.7],
      [1975630.5, 1249226, 3106, 1249226, 109, 293427, 7.71900, 7.52068, 7.48529, 7.65007, 6.9, 6.21882, 11.288,  6.0399,  9.1432, 107.482, 13686.5, 428126, 485145, 14623.0, 4.12507, 107.7, 1236760227, 0, 0, 0, 0, 297.286, 29728.6],
      [1976630.5, 1249226, 3105, 1249226, 110, 293428, 7.47000, 7.51429, 7.65170, 7.78935, 6.9, 6.22391, 11.288,  6.8993,  9.6609, 107.482, 13686.5, 428126, 485145, 14623.0, 4.12507, 107.7, 1236760228, 0, 0, 0, 0, 297.285, 29728.5],
      [1977630.5, 1249226, 3105, 1249226, 111, 293429, 7.47000, 7.52068, 7.65170, 7.81563, 6.9, 6.21628, 11.288, 12.9362, 10.8683, 107.482, 13686.5, 428126, 485145, 14623.0, 4.12507, 107.7, 1236760229, 0, 0, 0, 0, 297.286, 29728.6],
      [1978630.5, 1249226, 3105, 1249226, 112, 293430, 7.38700, 7.52108, 8.42847, 7.84192, 6.9, 6.21374, 11.288, 12.9427, 12.9391, 107.482, 13686.5, 428126, 485145, 14623.0, 4.12507, 107.7, 1236760230, 0, 0, 0, 0, 297.286, 29728.6],
      [1979630.5, 1249226, 3103, 1249226, 113, 293431, 7.38700, 7.50192, 8.42847, 7.91154, 6.9, 6.21628, 11.288, 15.5234, 13.9740, 107.482, 13686.5, 428126, 485145, 14623.0, 4.12507, 107.7, 1236760231, 0, 0, 0, 0, 297.286, 29728.6],
      [1980630.5, 1249226, 3103, 1249226, 114, 293432, 7.38700, 7.50192, 8.42847, 7.86265, 6.9, 6.21374, 11.288, 16.3941, 13.9753, 107.481, 13686.5, 428126, 485145, 14623.0, 4.12506, 107.7, 1236760232, 0, 0, 0, 0, 297.286, 29728.6],
      [1981630.5, 1249226, 3105, 1249226, 115, 293433, 7.47000, 7.48915, 8.42847, 7.81376, 6.9, 6.21628, 11.288, 12.0738, 14.2983, 107.481, 13686.5, 428126, 485145, 14623.0, 4.12506, 107.7, 1236760233, 0, 0, 0, 0, 297.285, 29728.5],
      [1982630.5, 1249226, 3105, 1249226, 116, 293434, 7.47000, 7.47000, 8.31421, 7.84968, 6.9, 6.22137, 11.288, 12.9427, 12.4010, 107.482, 13686.5, 428126, 485146, 14623.0, 4.12507, 107.7, 1236760234, 0, 0, 0, 0, 297.284, 29728.4],
      [1983630.5, 1249226, 3105, 1249226, 117, 293435, 7.47000, 7.47639, 7.38883, 7.87279, 6.9, 6.21596, 11.288, 14.5578, 11.3656, 107.481, 13686.5, 428126, 485146, 14623.0, 4.12506, 107.7, 1236760235, 0, 0, 0, 0, 297.285, 29728.5],
      [1984630.5, 1249226, 3105, 1249226, 118, 293436, 7.55300, 7.46362, 7.38883, 7.82670, 6.9, 6.21119, 11.288,  6.0369, 10.8482, 107.481, 13686.5, 428126, 485146, 14623.0, 4.12506, 107.7, 1236760236, 0, 0, 0, 0, 297.285, 29728.5],
      [1985630.5, 1249226, 3103, 1249226, 119, 293437, 7.47000, 7.47000, 7.95218, 7.72086, 6.9, 6.21628, 11.288, 11.2170, 10.1569, 107.480, 13686.5, 428127, 485146, 14623.0, 4.12505, 107.7, 1236760237, 0, 0, 0, 0, 297.283, 29728.3],
      [1986630.5, 1249226, 3103, 1249226, 120, 293438, 7.63600, 7.48277, 7.01615, 7.61502, 6.9, 6.21374, 11.288,  9.4865,  9.6601, 107.481, 13686.5, 428127, 485146, 14623.0, 4.12506, 107.7, 1236760238, 0, 0, 0, 0, 297.282, 29728.2],
      [1987630.5, 1249226, 3103, 1249226, 121, 293439, 7.47000, 7.48915, 7.01615, 7.48053, 6.9, 6.22391, 11.288,  9.4865, 10.0059, 107.481, 13686.5, 428127, 485146, 14623.0, 4.12506, 107.7, 1236760239, 0, 0, 0, 0, 297.282, 29728.2],
      [1988630.5, 1249226, 3103, 1249226, 122, 293440, 7.47000, 7.48277, 7.95218, 7.34603, 6.9, 6.21882, 11.288, 12.0738, 10.8672, 107.480, 13686.5, 428127, 485146, 14623.0, 4.12505, 107.7, 1236760240, 0, 0, 0, 0, 297.282, 29728.2],
      [1989630.5, 1249226, 3103, 1249226, 123, 293441, 7.55300, 7.48915, 7.95218, 7.17506, 6.9, 6.22137, 11.288,  7.7656, 11.5584, 107.481, 13686.5, 428127, 485146, 14623.0, 4.12506, 107.7, 1236760241, 0, 0, 0, 0, 297.283, 29728.3],
      [1990630.5, 1249226, 3105, 1249226, 124, 293442, 7.30400, 7.50113, 7.05256, 7.07527, 6.9, 6.21119, 11.288, 15.5234, 11.7319, 107.481, 13686.5, 428127, 485146, 14623.0, 4.12506, 107.7, 1236760242, 0, 0, 0, 0, 297.284, 29728.4],
      [1991630.5, 1249226, 3105, 1249226, 125, 293443, 7.47000, 7.48836, 7.05256, 6.97548, 6.9, 6.21628, 11.288, 12.9427, 11.0420, 107.480, 13686.5, 428127, 485146, 14623.0, 4.12505, 107.7, 1236760243, 0, 0, 0, 0, 297.282, 29728.2],
      [1992630.5, 1249226, 3105, 1249226, 126, 293444, 7.55300, 7.48836, 7.05256, 6.83236, 6.9, 6.21374, 11.288, 10.3541, 12.0774, 107.481, 13686.5, 428127, 485146, 14623.0, 4.12506, 107.7, 1236760244, 0, 0, 0, 0, 297.282, 29728.2],
      [1993630.5, 1249226, 3105, 1249226, 127, 293445, 7.47000, 7.46920, 6.68002, 6.84346, 6.9, 6.21628, 11.288,  8.6241, 12.2499, 107.481, 13686.5, 428127, 485146, 14623.0, 4.12506, 107.7, 1236760245, 0, 0, 0, 0, 297.282, 29728.2],
      [1994630.5, 1249226, 3103, 1249226, 128, 293446, 7.38700, 7.46920, 6.68002, 6.85457, 6.9, 6.21882, 11.288, 12.9427, 11.6024, 107.479, 13686.5, 428127, 485146, 14623.0, 4.12504, 107.7, 1236760246, 0, 0, 0, 0, 297.282, 29728.2],
      [1995630.5, 1249226, 3105, 1249226, 129, 293447, 7.55300, 7.47559, 6.09157, 6.77961, 6.9, 6.21882, 11.288, 16.3858, 11.2564, 107.479, 13686.5, 428127, 485146, 14623.0, 4.12504, 107.7, 1236760247, 0, 0, 0, 0, 297.282, 29728.2],
      [1996630.5, 1249226, 3105, 1249226, 130, 293448, 7.62562, 7.46282, 6.09157, 6.70465, 6.9, 6.21596, 11.288,  9.7052, 11.2573, 107.478, 13686.4, 428127, 485146, 14623.1, 4.12504, 107.7, 1236760248, 0, 0, 0, 0, 297.280, 29728.0],
      [1997630.5, 1249226, 3103, 1249226, 131, 293449, 7.38700, 7.47559, 6.09157, 6.71295, 6.9, 6.21628, 11.288,  8.6241, 10.7385, 107.479, 13686.4, 428127, 485146, 14623.1, 4.12504, 107.7, 1236760249, 0, 0, 0, 0, 297.280, 29728.0],
      [1998630.5, 1249226, 3105, 1249226, 132, 293450, 7.47000, 7.48197, 6.09157, 6.70720, 6.9, 6.21882, 11.288,  8.6285,  9.1870, 107.478, 13686.4, 428127, 485146, 14623.1, 4.12503, 107.7, 1236760250, 0, 0, 0, 0, 297.280, 29728.0],
      [1999630.5, 1249226, 3103, 1249226, 133, 293451, 7.38700, 7.48836, 7.16050, 6.70144, 6.9, 6.21374, 11.288, 10.3489,  9.8332, 107.479, 13686.4, 428127, 485146, 14623.1, 4.12504, 107.7, 1236760251, 0, 0, 0, 0, 297.280, 29728.0],
      [2000630.5, 1249226, 3105, 1249226, 134, 293452, 7.47000, 7.48836, 7.16050, 6.71429, 6.9, 6.21882, 11.288,  8.6285, 10.6969, 107.478, 13686.4, 428127, 485146, 14623.1, 4.12503, 107.7, 1236760252, 0, 0, 0, 0, 297.279, 29727.9],
      [2001630.5, 1249226, 3105, 1249226, 135, 293453, 7.55300, 7.47559, 6.97773, 6.72714, 6.9, 6.21628, 11.288, 12.9362, 10.3511, 107.478, 13686.4, 428127, 485146, 14623.1, 4.12503, 107.7, 1236760253, 0, 0, 0, 0, 297.280, 29728.0],
      [2002630.5, 1249226, 3105, 1249226, 136, 293454, 7.38700, 7.47559, 6.97773, 6.66953, 6.9, 6.22391, 11.288, 12.9427, 10.3522, 107.480, 13686.4, 428127, 485146, 14623.1, 4.12505, 107.7, 1236760254, 0, 0, 0, 0, 297.278, 29727.8],
      [2003630.5, 1249226, 3105, 1249226, 137, 293455, 7.47000, 7.46362, 7.16050, 6.57798, 6.9, 6.21628, 11.288,  6.8993,  9.4889, 107.479, 13686.4, 428127, 485146, 14623.1, 4.12504, 107.7, 1236760255, 0, 0, 0, 0, 297.278, 29727.8],
      [2004630.5, 1249226, 3102, 1249226, 138, 293456, 7.55300, 7.45723, 6.97773, 6.52038, 6.9, 6.21374, 11.288, 10.3541,  9.1439, 107.478, 13686.4, 428127, 485146, 14623.1, 4.12503, 107.7, 1236760256, 0, 0, 0, 0, 297.277, 29727.7],
      [2005630.5, 1249226, 3102, 1249226, 139, 293457, 7.63600, 7.45085, 6.97773, 6.60464, 6.9, 6.21628, 11.288,  4.3121,  8.4536, 107.478, 13686.4, 428127, 485146, 14623.1, 4.12503, 107.7, 1236760257, 0, 0, 0, 0, 297.276, 29727.6],
      [2006630.5, 1249226, 3103, 1249226, 140, 293458, 7.47000, 7.46362, 6.84703, 6.60668, 6.9, 6.21882, 11.288, 11.2114, 10.5252, 107.479, 13686.4, 428127, 485146, 14623.1, 4.12504, 107.7, 1236760258, 0, 0, 0, 0, 297.278, 29727.8],
      [2007630.5, 1249226, 3103, 1249226, 141, 293459, 7.22100, 7.46362, 6.84703, 6.71990, 6.9, 6.21374, 11.288,  9.4913, 10.5561, 107.479, 13686.4, 428127, 485146, 14623.1, 4.12504, 107.7, 1236760259, 0, 0, 0, 0, 297.277, 29727.7],
      [2008630.5, 1249226, 3105, 1249226, 142, 293460, 7.55300, 7.45085, 5.34276, 6.84719, 6.9, 6.21374, 11.288, 17.2569, 12.2823, 107.477, 13686.4, 428127, 485146, 14623.1, 4.12503, 107.7, 1236760260, 0, 0, 0, 0, 297.276, 29727.6],
      [2009630.5, 1249226, 3103, 1249226, 143, 293461, 7.47000, 7.43808, 4.90141, 6.97447, 6.9, 6.21596, 11.288, 10.5090, 12.1098, 107.478, 13686.4, 428127, 485146, 14623.1, 4.12503, 107.7, 1236760261, 0, 0, 0, 0, 297.274, 29727.4],
      [2010630.5, 1249226, 3103, 1249226, 144, 293462, 7.30400, 7.42531, 5.34276, 7.08442, 6.9, 6.21374, 11.288, 12.9427, 13.4887, 107.479, 13686.4, 428127, 485146, 14623.1, 4.12504, 107.7, 1236760262, 0, 0, 0, 0, 297.275, 29727.5],
      [2011630.5, 1249226, 3101, 1249226, 145, 293463, 7.38700, 7.41254, 7.18698, 7.16652, 6.9, 6.21882, 11.288, 10.3489, 14.3515, 107.478, 13686.4, 428127, 485147, 14623.1, 4.12503, 107.7, 1236760263, 0, 0, 0, 0, 297.275, 29727.5],
      [2012630.5, 1249226, 3102, 1249226, 146, 293464, 7.55300, 7.39338, 7.18698, 7.12995, 6.9, 6.21374, 11.288, 16.3858, 13.4577, 107.478, 13686.4, 428127, 485147, 14623.1, 4.12503, 107.7, 1236760264, 0, 0, 0, 0, 297.275, 29727.5],
      [2013630.5, 1249226, 3103, 1249226, 147, 293465, 7.47000, 7.39977, 8.63240, 7.15379, 6.9, 6.21628, 11.288, 21.5711, 12.4215, 107.477, 13686.4, 428127, 485147, 14623.1, 4.12502, 107.7, 1236760265, 0, 0, 0, 0, 297.275, 29727.5],
      [2014630.5, 1249226, 3102, 1249226, 148, 293466, 7.38700, 7.41254, 8.63240, 7.17762, 6.9, 6.21628, 11.288,  6.0399, 13.2854, 107.478, 13686.3, 428128, 485147, 14623.1, 4.12503, 107.7, 1236760266, 0, 0, 0, 0, 297.273, 29727.3],
      [2015630.5, 1249226, 3103, 1249226, 149, 293467, 7.22100, 7.40615, 8.63240, 7.26682, 6.9, 6.21882, 11.288,  7.7617, 12.4230, 107.478, 13686.3, 428128, 485147, 14623.1, 4.12503, 107.7, 1236760267, 0, 0, 0, 0, 297.272, 29727.2],
      [2016630.5, 1249226, 3102, 1249226, 150, 293468, 7.30400, 7.39338, 8.58983, 7.38085, 6.9, 6.21374, 11.288, 14.6684, 10.8699, 107.478, 13686.3, 428128, 485147, 14623.1, 4.12503, 107.7, 1236760268, 0, 0, 0, 0, 297.272, 29727.2],
      [2017630.5, 1249226, 3102, 1249226, 151, 293469, 7.38700, 7.40615, 8.04503, 7.46092, 6.9, 6.21374, 11.288, 12.0738, 11.7317, 107.477, 13686.3, 428128, 485147, 14623.1, 4.12503, 107.7, 1236760269, 0, 0, 0, 0, 297.273, 29727.3],
      [2018630.5, 1249226, 3102, 1249226, 152, 293470, 7.38700, 7.38062, 6.50234, 7.39913, 6.9, 6.21882, 11.288, 13.8055, 13.2840, 107.477, 13686.3, 428128, 485147, 14623.1, 4.12502, 107.7, 1236760270, 0, 0, 0, 0, 297.272, 29727.2],
      [2019630.5, 1249226, 3103, 1249226, 153, 293471, 7.55300, 7.37423, 7.15689, 7.33735, 6.9, 6.21882, 11.288, 10.3489, 12.4531, 107.477, 13686.3, 428128, 485147, 14623.1, 4.12502, 107.7, 1236760271, 0, 0, 0, 0, 297.269, 29726.9],
      [2020630.5, 1249226, 3103, 1249226, 154, 293472, 7.38700, 7.36785, 7.15689, 7.16437, 6.9, 6.21374, 11.288, 15.5234, 11.5915, 107.477, 13686.3, 428128, 485147, 14623.1, 4.12502, 107.7, 1236760272, 0, 0, 0, 0, 297.269, 29726.9],
      [2021630.5, 1249226, 3102, 1249226, 155, 293473, 7.47000, 7.36785, 6.50234, 6.94869, 6.9, 6.22073, 11.288, 10.5139, 11.0727, 107.476, 13686.3, 428128, 485147, 14623.1, 4.12502, 107.7, 1236760273, 0, 0, 0, 0, 297.269, 29726.9],
      [2022630.5, 1249226, 3102, 1249226, 156, 293474, 7.30400, 7.38700, 6.38375, 6.73301, 6.9, 6.21119, 11.288,  7.7656, 12.9720, 107.477, 13686.3, 428128, 485147, 14623.1, 4.12502, 107.7, 1236760274, 0, 0, 0, 0, 297.269, 29726.9],
      [2023630.5, 1249226, 3103, 1249226, 157, 293475, 7.47000, 7.38700, 6.38375, 6.52061, 6.9, 6.21882, 11.288, 11.2114, 12.2820, 107.477, 13686.3, 428128, 485147, 14623.1, 4.12503, 107.7, 1236760275, 0, 0, 0, 0, 297.268, 29726.8],
      [2024630.5, 1249226, 3102, 1249226, 158, 293476, 7.05500, 7.39338, 6.38375, 6.36242, 6.9, 6.22137, 11.288, 19.8454, 12.9403, 107.477, 13686.3, 428128, 485147, 14623.1, 4.12503, 107.7, 1236760276, 0, 0, 0, 0, 297.268, 29726.8],
      [2025630.5, 1249226, 3103, 1249226, 159, 293477, 7.47000, 7.41892, 6.38375, 6.44281, 6.9, 6.21374, 11.288, 12.0738, 12.7671, 107.476, 13686.3, 428128, 485147, 14623.1, 4.12501, 107.7, 1236760277, 0, 0, 0, 0, 297.267, 29726.7],
      [2026630.5, 1249226, 3102, 1249226, 160, 293478, 7.38700, 7.40615, 6.38375, 6.55337, 6.9, 6.21374, 11.288, 13.8055, 12.7682, 107.477, 13686.2, 428128, 485147, 14623.1, 4.12502, 107.7, 1236760278, 0, 0, 0, 0, 297.266, 29726.6],
      [2027630.5, 1249226, 3102, 1249226, 161, 293479, 7.38700, 7.41254, 5.82856, 6.66393, 6.9, 6.21374, 11.288,  6.8993, 12.4212, 107.476, 13686.2, 428128, 485147, 14623.1, 4.12502, 107.7, 1236760279, 0, 0, 0, 0, 297.266, 29726.6],
      [2028630.5, 1249226, 3102, 1249226, 162, 293480, 7.47000, 7.41852, 5.82856, 6.78868, 6.9, 6.22137, 11.288, 11.2170, 12.5950, 107.477, 13686.2, 428128, 485147, 14623.1, 4.12502, 107.7, 1236760280, 0, 0, 0, 0, 297.265, 29726.5],
      [2029630.5, 1249226, 3103, 1249226, 163, 293481, 7.30400, 7.43768, 5.82856, 6.88521, 6.9, 6.21882, 11.288, 18.1107, 12.5936, 107.476, 13686.2, 428128, 485147, 14623.1, 4.12501, 107.7, 1236760281, 0, 0, 0, 0, 297.265, 29726.5],
      [2030630.5, 1249226, 3102, 1249226, 164, 293482, 7.47000, 7.41214, 5.98859, 7.01908, 6.9, 6.21374, 11.288, 12.9427, 13.6285, 107.475, 13686.2, 428128, 485147, 14623.1, 4.12501, 107.7, 1236760282, 0, 0, 0, 0, 297.264, 29726.4],
      [2031630.5, 1249226, 3103, 1249226, 165, 293483, 7.71900, 7.44406, 7.54734, 7.11561, 6.9, 6.21374, 11.288, 13.7986, 14.6640, 107.476, 13686.2, 428128, 485147, 14623.1, 4.12502, 107.7, 1236760283, 0, 0, 0, 0, 297.263, 29726.3],
      [2032630.5, 1249226, 3103, 1249226, 166, 293484, 7.38700, 7.45045, 8.59419, 7.24948, 6.9, 6.22137, 11.288, 12.0738, 13.1446, 107.476, 13686.2, 428128, 485147, 14623.1, 4.12502, 107.7, 1236760284, 0, 0, 0, 0, 297.261, 29726.1],
      [2033630.5, 1249226, 3102, 1249226, 167, 293485, 7.47000, 7.44406, 8.59419, 7.38998, 6.9, 6.21628, 11.288, 16.3941, 13.8332, 107.475, 13686.2, 428128, 485147, 14623.1, 4.12501, 107.7, 1236760285, 0, 0, 0, 0, 297.260, 29726.0],
      [2034630.5, 1249226, 3101, 1249226, 168, 293486, 7.54781, 7.43129, 8.12403, 7.57319, 6.9, 6.21358, 11.288, 10.5139, 14.3507, 107.476, 13686.2, 428128, 485147, 14623.1, 4.12501, 107.7, 1236760286, 0, 0, 0, 0, 297.261, 29726.1],
      [2035630.5, 1249226, 3102, 1249226, 169, 293487, 7.55300, 7.43768, 7.63870, 7.73066, 6.9, 6.21374, 11.288, 16.3858, 14.8696, 107.476, 13686.2, 428128, 485147, 14623.1, 4.12502, 107.7, 1236760287, 0, 0, 0, 0, 297.261, 29726.1],
      [2036630.5, 1249226, 3102, 1249226, 170, 293488, 7.13800, 7.44406, 8.12403, 7.88814, 6.9, 6.21628, 11.288, 16.3858, 13.6606, 107.475, 13686.1, 428128, 485148, 14623.1, 4.12501, 107.7, 1236760288, 0, 0, 0, 0, 297.259, 29725.9],
      [2037630.5, 1249226, 3103, 1249226, 171, 293489, 7.47000, 7.44406, 7.63870, 8.03280, 6.9, 6.21374, 11.288, 14.6684, 13.6286, 107.476, 13686.1, 428128, 485148, 14623.1, 4.12501, 107.7, 1236760289, 0, 0, 0, 0, 297.257, 29725.7],
      [2038630.5, 1249226, 3102, 1249226, 172, 293490, 7.55300, 7.38022, 8.12403, 7.97147, 6.9, 6.21628, 11.288, 10.3489, 13.4561, 107.476, 13686.1, 428128, 485148, 14623.1, 4.12501, 107.7, 1236760290, 0, 0, 0, 0, 297.256, 29725.6],
      [2039630.5, 1249226, 3103, 1249226, 173, 293491, 7.30400, 7.37383, 8.21025, 7.76826, 6.9, 6.21628, 11.288, 10.3541, 11.5595, 107.475, 13686.1, 428128, 485148, 14623.1, 4.12501, 107.7, 1236760291, 0, 0, 0, 0, 297.257, 29725.7],
      [2040630.5, 1249226, 3103, 1249226, 174, 293492, 7.22100, 7.36106, 8.21025, 7.56505, 6.9, 6.21882, 11.288, 15.5234, 11.3856, 107.474, 13686.1, 428128, 485148, 14623.1, 4.12499, 107.7, 1236760292, 0, 0, 0, 0, 297.256, 29725.6],
      [2041630.5, 1249226, 3103, 1249226, 175, 293493, 7.55300, 7.32515, 7.87579, 7.49279, 6.9, 6.21374, 11.288,  6.9028, 11.7318, 107.474, 13686.1, 428128, 485148, 14623.1, 4.12500, 107.7, 1236760293, 0, 0, 0, 0, 297.256, 29725.6],
      [2042630.5, 1249226, 3102, 1249226, 176, 293494, 7.38700, 7.32515, 7.87579, 7.35769, 6.9, 6.21628, 11.288, 13.7986, 12.5931, 107.474, 13686.1, 428129, 485148, 14623.1, 4.12500, 107.7, 1236760294, 0, 0, 0, 0, 297.255, 29725.5],
      [2043630.5, 1249226, 3101, 1249226, 177, 293495, 7.47000, 7.35707, 7.86906, 7.19469, 6.9, 6.21374, 11.288, 12.0798, 11.7318, 107.476, 13686.1, 428129, 485148, 14623.1, 4.12501, 107.7, 1236760295, 0, 0, 0, 0, 297.254, 29725.4],
      [2044630.5, 1249226, 3102, 1249226, 178, 293496, 6.88900, 7.34430, 6.75006, 7.06902, 6.9, 6.21882, 11.288, 14.6610, 12.4211, 107.476, 13686.1, 428129, 485148, 14623.1, 4.12501, 107.7, 1236760296, 0, 0, 0, 0, 297.254, 29725.4],
      [2045630.5, 1249226, 3103, 1249226, 179, 293497, 7.30400, 7.32515, 5.95251, 6.90602, 6.9, 6.21882, 11.288, 11.2170, 12.8964, 107.475, 13686.1, 428129, 485148, 14623.1, 4.12500, 107.7, 1236760297, 0, 0, 0, 0, 297.252, 29725.2],
      [2046630.5, 1249226, 3102, 1249226, 180, 293498, 7.30400, 7.35707, 5.95251, 6.72695, 6.9, 6.21628, 11.288, 10.3489, 13.7576, 107.474, 13686.1, 428129, 485148, 14623.1, 4.12500, 107.7, 1236760298, 0, 0, 0, 0, 297.253, 29725.3],
      [2047630.5, 1249226, 3102, 1249226, 181, 293499, 7.08094, 7.38900, 7.18464, 6.55731, 6.9, 6.21358, 11.288, 16.1753, 12.2060, 107.475, 13686.0, 428129, 485148, 14623.1, 4.12500, 107.7, 1236760299, 0, 0, 0, 0, 297.252, 29725.2],
      [2048630.5, 1249226, 3101, 1249226, 182, 293500, 7.55300, 7.35707, 5.88234, 6.46871, 6.9, 6.22137, 11.288, 16.3858, 12.5498, 107.475, 13686.0, 428129, 485148, 14623.1, 4.12501, 107.7, 1236760300, 0, 0, 0, 0, 297.250, 29725.0],
      [2049630.5, 1249226, 3102, 1249226, 183, 293501, 7.55300, 7.36984, 6.00500, 6.38012, 6.9, 6.21628, 11.288,  6.9028, 13.9314, 107.474, 13686.0, 428129, 485148, 14623.1, 4.12500, 107.7, 1236760301, 0, 0, 0, 0, 297.250, 29725.0],
      [2050630.5, 1249226, 3103, 1249226, 184, 293502, 7.30400, 7.34430, 6.00500, 6.32245, 6.9, 6.21628, 11.288, 12.9362, 13.4561, 107.473, 13686.0, 428129, 485148, 14623.1, 4.12499, 107.7, 1236760302, 0, 0, 0, 0, 297.250, 29725.0],
      [2051630.5, 1249226, 3102, 1249226, 185, 293503, 7.30400, 7.36984, 6.00500, 6.36986, 6.9, 6.21119, 11.288, 17.2569, 13.8028, 107.474, 13686.0, 428129, 485148, 14623.1, 4.12500, 107.7, 1236760303, 0, 0, 0, 0, 297.249, 29724.9],
      [2052630.5, 1249226, 3101, 1249226, 186, 293504, 7.71900, 7.37623, 5.88234, 6.52633, 6.9, 6.21374, 11.288, 13.7986, 15.0095, 107.473, 13686.0, 428129, 485148, 14623.1, 4.12499, 107.7, 1236760304, 0, 0, 0, 0, 297.248, 29724.8],
      [2053630.5, 1249226, 3102, 1249226, 187, 293505, 7.63600, 7.37104, 6.00500, 6.68281, 6.9, 6.21374, 11.288, 18.1198, 14.3205, 107.474, 13686.0, 428129, 485148, 14623.1, 4.12500, 107.7, 1236760305, 0, 0, 0, 0, 297.246, 29724.6],
      [2054630.5, 1249226, 3101, 1249226, 188, 293506, 7.13800, 7.39458, 6.72402, 6.74451, 6.9, 6.21628, 11.288, 12.9362, 13.1114, 107.474, 13686.0, 428129, 485148, 14623.1, 4.12500, 107.7, 1236760306, 0, 0, 0, 0, 297.246, 29724.6],
      [2055630.5, 1249226, 3101, 1249226, 189, 293507, 7.55300, 7.35627, 6.72402, 6.90639, 6.9, 6.21119, 11.288,  9.4913, 12.2500, 107.474, 13686.0, 428129, 485148, 14623.1, 4.12499, 107.7, 1236760307, 0, 0, 0, 0, 297.246, 29724.6],
      [2056630.5, 1249226, 3102, 1249226, 190, 293508, 7.13800, 7.30520, 7.11944, 7.05883, 6.9, 6.21374, 11.288, 11.2114, 10.1784, 107.473, 13686.0, 428129, 485148, 14623.1, 4.12499, 107.7, 1236760308, 0, 0, 0, 0, 297.246, 29724.6],
      [2057630.5, 1249226, 3101, 1249226, 191, 293509, 7.22100, 7.29243, 7.36632, 7.06897, 6.9, 6.21628, 11.288,  9.4913,  9.2087, 107.473, 13686.0, 428129, 485148, 14623.1, 4.12499, 107.7, 1236760309, 0, 0, 0, 0, 297.245, 29724.5],
      [2058630.5, 1249226, 3100, 1249226, 192, 293510, 7.38700, 7.29881, 7.98672, 7.08488, 6.9, 6.22137, 11.288,  7.7617,  8.8627, 107.473, 13685.9, 428129, 485148, 14623.1, 4.12499, 107.7, 1236760310, 0, 0, 0, 0, 297.244, 29724.4],
      [2059630.5, 1249226, 3101, 1249226, 193, 293511, 7.23656, 7.33074, 7.98672, 7.11023, 6.9, 6.21119, 11.288,  8.0877,  9.5541, 107.473, 13685.9, 428129, 485148, 14623.1, 4.12499, 107.7, 1236760311, 0, 0, 0, 0, 297.242, 29724.2],
      [2060630.5, 1249226, 3100, 1249226, 194, 293512, 7.38700, 7.33712, 7.98672, 7.12615, 6.9, 6.21628, 11.288,  7.7617, 10.4156, 107.473, 13685.9, 428129, 485148, 14623.1, 4.12499, 107.7, 1236760312, 0, 0, 0, 0, 297.241, 29724.1],
      [2061630.5, 1249226, 3102, 1249226, 195, 293513, 7.05500, 7.34351, 7.98672, 7.08675, 6.9, 6.21882, 11.288, 14.6684, 11.1067, 107.473, 13685.9, 428129, 485148, 14623.1, 4.12498, 107.7, 1236760313, 0, 0, 0, 0, 297.241, 29724.1],
      [2062630.5, 1249226, 3103, 1249226, 196, 293514, 6.88900, 7.35627, 7.98672, 7.09580, 6.9, 6.21628, 11.288, 13.7986, 11.3864, 107.473, 13685.9, 428129, 485148, 14623.1, 4.12499, 107.7, 1236760314, 0, 0, 0, 0, 297.240, 29724.0],
      [2063630.5, 1249226, 3101, 1249226, 197, 293515, 7.13800, 7.42012, 6.13685, 7.07443, 6.9, 6.21628, 11.288, 11.2170, 11.0421, 107.472, 13685.9, 428129, 485148, 14623.1, 4.12498, 107.7, 1236760315, 0, 0, 0, 0, 297.240, 29724.0],
      [2064630.5, 1249226, 3101, 1249226, 198, 293516, 7.38700, 7.43289, 6.21188, 7.03408, 6.9, 6.21374, 11.288,  9.4865, 11.0406, 107.472, 13685.9, 428129, 485148, 14623.1, 4.12498, 107.7, 1236760316, 0, 0, 0, 0, 297.238, 29723.8],
      [2065630.5, 1249226, 3101, 1249226, 199, 293517, 8.13400, 7.45843, 6.21188, 6.91436, 6.9, 6.21374, 11.288,  6.0399, 11.0420, 107.473, 13685.8, 428129, 485148, 14623.1, 4.12499, 107.7, 1236760317, 0, 0, 0, 0, 297.238, 29723.8],
      [2066630.5, 1249226, 3101, 1249226, 200, 293518, 7.71900, 7.44047, 6.21188, 6.79464, 6.9, 6.21374, 11.288, 14.6610, 11.0409, 107.473, 13685.8, 428129, 485149, 14623.1, 4.12499, 107.7, 1236760318, 0, 0, 0, 0, 297.237, 29723.7],
      [2067630.5, 1249226, 3102, 1249226, 201, 293519, 7.22100, 7.47239, 6.21188, 6.67492, 6.9, 6.21119, 11.288, 13.8055, 11.3870, 107.474, 13685.8, 428129, 485149, 14623.1, 4.12499, 107.7, 1236760319, 0, 0, 0, 0, 297.237, 29723.7],
      [2068630.5, 1249226, 3101, 1249226, 202, 293520, 7.71900, 7.54901, 6.84166, 6.58536, 6.9, 6.21374, 11.288, 11.2114, 12.0763, 107.474, 13685.8, 428129, 485149, 14623.1, 4.12499, 107.7, 1236760320, 0, 0, 0, 0, 297.235, 29723.5],
      [2069630.5, 1249226, 3100, 1249226, 203, 293521, 7.96800, 7.58093, 6.84166, 6.49579, 6.9, 6.21628, 11.288, 11.2170, 12.2503, 107.472, 13685.8, 428129, 485149, 14623.1, 4.12498, 107.7, 1236760321, 0, 0, 0, 0, 297.235, 29723.5],
      [2070630.5, 1249226, 3100, 1249226, 204, 293522, 7.38700, 7.60647, 6.84166, 6.54852, 6.9, 6.21628, 11.288,  9.4865, 11.4293, 107.472, 13685.8, 428129, 485149, 14623.1, 4.12498, 107.7, 1236760322, 0, 0, 0, 0, 297.234, 29723.4],
      [2071630.5, 1249226, 3100, 1249226, 205, 293523, 7.71900, 7.61286, 6.43039, 6.48315, 6.9, 6.21628, 11.288, 15.5312, 11.2579, 107.472, 13685.8, 428130, 485149, 14623.1, 4.12498, 107.7, 1236760323, 0, 0, 0, 0, 297.233, 29723.3],
      [2072630.5, 1249226, 3101, 1249226, 206, 293524, 7.00312, 7.57455, 6.43039, 6.41279, 6.9, 6.21358, 11.288,  9.7006, 12.6366, 107.473, 13685.8, 428130, 485149, 14623.1, 4.12499, 107.7, 1236760324, 0, 0, 0, 0, 297.232, 29723.2],
      [2073630.5, 1249226, 3101, 1249226, 207, 293525, 7.80200, 7.51709, 6.43039, 6.34242, 6.9, 6.21882, 11.288, 10.3541, 13.3279, 107.474, 13685.8, 428130, 485149, 14623.1, 4.12499, 107.7, 1236760325, 0, 0, 0, 0, 297.232, 29723.2],
      [2074630.5, 1249226, 3100, 1249226, 208, 293526, 8.05100, 7.53624, 6.82238, 6.27705, 6.9, 6.21374, 11.288, 18.1107, 12.8089, 107.474, 13685.7, 428130, 485149, 14623.1, 4.12500, 107.7, 1236760326, 0, 0, 0, 0, 297.230, 29723.0],
      [2075630.5, 1249226, 3102, 1249226, 209, 293527, 7.30400, 7.51709, 6.82238, 6.21277, 6.9, 6.21374, 11.288, 12.9427, 12.5944, 107.472, 13685.7, 428130, 485149, 14623.1, 4.12498, 107.7, 1236760327, 0, 0, 0, 0, 297.230, 29723.0],
      [2076630.5, 1249226, 3101, 1249226, 210, 293528, 7.47000, 7.46601, 6.82238, 6.26517, 6.9, 6.22137, 11.288, 12.9362, 12.9384, 107.473, 13685.7, 428130, 485149, 14623.1, 4.12499, 107.7, 1236760328, 0, 0, 0, 0, 297.229, 29722.9],
      [2077630.5, 1249226, 3102, 1249226, 211, 293529, 7.47000, 7.44686, 5.36207, 6.31756, 6.9, 6.21374, 11.288,  8.6285, 12.2499, 107.473, 13685.7, 428130, 485149, 14623.1, 4.12499, 107.7, 1236760329, 0, 0, 0, 0, 297.229, 29722.9],
      [2078630.5, 1249226, 3101, 1249226, 212, 293530, 7.63600, 7.43409, 5.29709, 6.28492, 6.9, 6.21628, 11.288, 12.0738, 11.9036, 107.471, 13685.7, 428130, 485149, 14623.1, 4.12497, 107.7, 1236760330, 0, 0, 0, 0, 297.229, 29722.9],
      [2079630.5, 1249226, 3101, 1249226, 213, 293531, 6.97200, 7.42212, 5.29709, 6.26535, 6.9, 6.21119, 11.288, 14.6684, 12.2486, 107.470, 13685.7, 428130, 485149, 14623.1, 4.12496, 107.7, 1236760331, 0, 0, 0, 0, 297.228, 29722.8],
      [2080630.5, 1249226, 3100, 1249226, 214, 293532, 7.47000, 7.32635, 5.36207, 6.24578, 6.9, 6.22137, 11.288, 11.2114, 12.0760, 107.471, 13685.7, 428130, 485149, 14623.1, 4.12497, 107.7, 1236760332, 0, 0, 0, 0, 297.227, 29722.6],
      [2081630.5, 1249226, 3101, 1249226, 215, 293533, 7.47000, 7.22419, 6.00607, 6.09736, 6.9, 6.21628, 11.288, 14.6610, 12.9384, 107.469, 13685.7, 428130, 485149, 14623.1, 4.12495, 107.7, 1236760333, 0, 0, 0, 0, 297.227, 29722.7],
      [2082630.5, 1249226, 3100, 1249226, 216, 293534, 7.30400, 7.30719, 7.52282, 5.94655, 6.9, 6.21374, 11.288,  7.7656, 13.1110, 107.469, 13685.7, 428130, 485149, 14623.1, 4.12496, 107.7, 1236760334, 0, 0, 0, 0, 297.228, 29722.8],
      [2083630.5, 1249226, 3100, 1249226, 217, 293535, 7.13800, 7.26888, 7.52282, 5.87097, 6.9, 6.21882, 11.288, 16.3858, 12.9715, 107.470, 13685.7, 428130, 485149, 14623.1, 4.12497, 107.7, 1236760335, 0, 0, 0, 0, 297.227, 29722.7],
      [2084630.5, 1249226, 3102, 1249226, 218, 293536, 7.55300, 7.30081, 6.00607, 5.90772, 6.9, 6.22137, 11.288, 15.5312, 13.1440, 107.471, 13685.7, 428130, 485149, 14623.1, 4.12497, 107.7, 1236760336, 0, 0, 0, 0, 297.226, 29722.6],
      [2085630.5, 1249226, 3101, 1249226, 219, 293537, 6.84750, 7.26888, 6.17597, 5.94947, 6.9, 6.21119, 11.288, 10.5139, 14.5246, 107.472, 13685.6, 428130, 485149, 14623.1, 4.12498, 107.7, 1236760337, 0, 0, 0, 0, 297.223, 29722.3],
      [2086630.5, 1249226, 3101, 1249226, 220, 293538, 6.55700, 7.28165, 6.17597, 6.00909, 6.9, 6.22137, 11.288, 15.5234, 12.2823, 107.472, 13685.6, 428130, 485149, 14623.1, 4.12498, 107.7, 1236760338, 0, 0, 0, 0, 297.223, 29722.3],
      [2087630.5, 1249226, 3101, 1249226, 221, 293539, 6.72300, 7.29442, 4.89289, 6.08043, 6.9, 6.21374, 11.288, 14.6684, 10.9017, 107.471, 13685.7, 428130, 485149, 14623.1, 4.12497, 107.7, 1236760339, 0, 0, 0, 0, 297.224, 29722.4],
      [2088630.5, 1249226, 3101, 1249226, 222, 293540, 8.38300, 7.22419, 4.86182, 6.18501, 6.9, 6.21374, 11.288,  5.1745, 11.3862, 107.473, 13685.7, 428130, 485149, 14623.1, 4.12499, 107.7, 1236760340, 0, 0, 0, 0, 297.224, 29722.4],
      [2089630.5, 1249226, 3100, 1249226, 223, 293541, 6.97200, 7.20504, 5.83986, 6.11595, 6.9, 6.21119, 11.288,  8.6285, 10.1788, 107.471, 13685.6, 428130, 485149, 14623.1, 4.12497, 107.7, 1236760341, 0, 0, 0, 0, 297.223, 29722.3],
      [2090630.5, 1249226, 3100, 1249226, 224, 293542, 7.88500, 7.28804, 5.83986, 6.02108, 6.9, 6.21374, 11.288, 12.9362,  9.4885, 107.471, 13685.6, 428130, 485149, 14623.1, 4.12497, 107.7, 1236760342, 0, 0, 0, 0, 297.222, 29722.2],
      [2091630.5, 1249226, 3101, 1249226, 225, 293543, 7.22100, 7.26968, 5.83986, 6.04288, 6.9, 6.22137, 11.288,  9.4865, 10.6959, 107.471, 13685.6, 428130, 485149, 14623.1, 4.12497, 107.7, 1236760343, 0, 0, 0, 0, 297.221, 29722.2],
      [2092630.5, 1249226, 3100, 1249226, 226, 293544, 7.13800, 7.27287, 6.07205, 6.05893, 6.9, 6.21374, 11.288, 11.2170, 12.7667, 107.472, 13685.6, 428130, 485150, 14623.1, 4.12498, 107.7, 1236760344, 0, 0, 0, 0, 297.222, 29722.2],
      [2093630.5, 1249226, 3100, 1249226, 227, 293545, 7.63600, 7.38141, 6.28950, 5.99077, 6.9, 6.21374, 11.288, 11.2114, 12.7667, 107.471, 13685.6, 428130, 485149, 14623.1, 4.12497, 107.7, 1236760345, 0, 0, 0, 0, 297.221, 29722.2],
      [2094630.5, 1249226, 3100, 1249226, 228, 293546, 6.55700, 7.40695, 7.36566, 6.02131, 6.9, 6.21628, 11.288, 18.9826, 14.3208, 107.470, 13685.6, 428130, 485150, 14623.1, 4.12496, 107.7, 1236760346, 0, 0, 0, 0, 297.220, 29722.0],
      [2095630.5, 1249226, 3100, 1249226, 229, 293547, 7.05500, 7.34311, 6.62508, 6.12370, 6.9, 6.21628, 11.288, 12.9362, 14.8272, 107.471, 13685.6, 428130, 485150, 14623.1, 4.12497, 107.7, 1236760347, 0, 0, 0, 0, 297.220, 29722.0],
      [2096630.5, 1249226, 3101, 1249226, 230, 293548, 8.21700, 7.41334, 6.28950, 6.16560, 6.9, 6.21882, 11.288, 17.2569, 14.9997, 107.471, 13685.6, 428130, 485150, 14623.1, 4.12497, 107.7, 1236760348, 0, 0, 0, 0, 297.220, 29722.0],
      [2097630.5, 1249226, 3100, 1249226, 231, 293549, 7.31437, 7.36226, 6.28950, 6.27449, 6.9, 6.22073, 11.288, 13.7490, 14.9997, 107.471, 13685.6, 428130, 485150, 14623.1, 4.12497, 107.7, 1236760349, 0, 0, 0, 0, 297.221, 29722.1],
      [2098630.5, 1249226, 3101, 1249226, 232, 293550, 6.88900, 7.39418, 6.38462, 6.43251, 6.9, 6.21628, 11.288, 12.0738, 14.4823, 107.471, 13685.6, 428130, 485150, 14623.1, 4.12497, 107.7, 1236760350, 0, 0, 0, 0, 297.220, 29722.0],
      [2099630.5, 1249226, 3099, 1249226, 233, 293551, 7.96800, 7.41334, 5.28984, 6.58710, 6.9, 6.21628, 11.288, 18.9826, 13.6194, 107.470, 13685.6, 428130, 485150, 14623.1, 4.12496, 107.7, 1236760351, 0, 0, 0, 0, 297.218, 29721.8],
      [2100630.5, 1249226, 3100, 1249226, 234, 293552, 7.05500, 7.38780, 5.28984, 6.72496, 6.9, 6.21882, 11.288, 10.3489, 12.9394, 107.470, 13685.6, 428130, 485150, 14623.1, 4.12496, 107.7, 1236760352, 0, 0, 0, 0, 297.218, 29721.8],
      [2101630.5, 1249226, 3100, 1249226, 235, 293553, 7.55300, 7.47718, 6.19291, 6.76561, 6.9, 6.21119, 11.288, 12.9427, 12.4219, 107.470, 13685.6, 428131, 485150, 14623.1, 4.12496, 107.7, 1236760353, 0, 0, 0, 0, 297.218, 29721.8],
      [2102630.5, 1249226, 3101, 1249226, 236, 293554, 7.88500, 7.54741, 6.38462, 6.84660, 6.9, 6.21628, 11.288, 10.3489,  9.8334, 107.470, 13685.6, 428131, 485150, 14623.1, 4.12496, 107.7, 1236760354, 0, 0, 0, 0, 297.218, 29721.8],
      [2103630.5, 1249226, 3101, 1249226, 237, 293555, 7.22100, 7.40695, 7.25540, 6.89750, 6.9, 6.21628, 11.288,  9.4865, 10.5233, 107.470, 13685.6, 428131, 485150, 14623.1, 4.12496, 107.7, 1236760355, 0, 0, 0, 0, 297.219, 29721.9],
      [2104630.5, 1249226, 3099, 1249226, 238, 293556, 7.63600, 7.44885, 7.89409, 6.88174, 6.9, 6.22137, 11.288,  6.0399,  9.6605, 107.470, 13685.6, 428131, 485150, 14623.1, 4.12496, 107.7, 1236760356, 0, 0, 0, 0, 297.217, 29721.7],
      [2105630.5, 1249226, 3099, 1249226, 239, 293557, 7.38700, 7.41054, 8.08171, 6.81672, 6.9, 6.21119, 11.288, 13.7986,  9.8330, 107.470, 13685.5, 428131, 485150, 14623.1, 4.12496, 107.7, 1236760357, 0, 0, 0, 0, 297.216, 29721.6],
      [2106630.5, 1249226, 3099, 1249226, 240, 293558, 7.30400, 7.34670, 8.08171, 6.79581, 6.9, 6.22391, 11.288,  8.6285, 10.3516, 107.471, 13685.6, 428131, 485150, 14623.1, 4.12497, 107.7, 1236760358, 0, 0, 0, 0, 297.217, 29721.7],
      [2107630.5, 1249226, 3100, 1249226, 241, 293559, 7.71900, 7.36585, 7.89409, 6.76988, 6.9, 6.21374, 11.288, 11.2114, 13.8007, 107.470, 13685.6, 428131, 485150, 14623.1, 4.12497, 107.7, 1236760359, 0, 0, 0, 0, 297.217, 29721.7],
      [2108630.5, 1249226, 3100, 1249226, 242, 293560, 7.96800, 7.39777, 7.67794, 6.67447, 6.9, 6.21882, 11.288, 12.0798, 13.3055, 107.470, 13685.5, 428131, 485150, 14623.1, 4.12496, 107.7, 1236760360, 0, 0, 0, 0, 297.215, 29721.5],
      [2109630.5, 1249226, 3099, 1249226, 243, 293561, 6.39100, 7.37224, 6.95128, 6.56935, 6.9, 6.21374, 11.288, 23.2851, 13.9946, 107.471, 13685.5, 428131, 485150, 14623.1, 4.12497, 107.7, 1236760361, 0, 0, 0, 0, 297.213, 29721.3],
      [2110630.5, 1249226, 3099, 1249226, 244, 293562, 7.85906, 7.49354, 6.08461, 6.54971, 6.9, 6.22312, 11.288, 11.3227, 13.8231, 107.471, 13685.5, 428131, 485150, 14623.1, 4.12497, 107.7, 1236760362, 0, 0, 0, 0, 297.214, 29721.4],
      [2111630.5, 1249226, 3099, 1249226, 245, 293563, 6.39100, 7.38500, 5.53925, 6.48093, 6.9, 6.21374, 11.288, 12.0738, 14.5118, 107.471, 13685.5, 428131, 485150, 14623.1, 4.12497, 107.7, 1236760363, 0, 0, 0, 0, 297.215, 29721.5],
      [2112630.5, 1249226, 3100, 1249226, 246, 293564, 7.13800, 7.39139, 5.01813, 6.39773, 6.9, 6.21374, 11.288, 10.3541, 12.6159, 107.471, 13685.5, 428131, 485150, 14623.1, 4.12497, 107.7, 1236760364, 0, 0, 0, 0, 297.214, 29721.4],
      [2113630.5, 1249226, 3100, 1249226, 247, 293565, 7.30400, 7.42331, 4.95262, 6.31452, 6.9, 6.21882, 11.288, 15.5234, 13.6285, 107.471, 13685.5, 428131, 485150, 14623.1, 4.12497, 107.7, 1236760365, 0, 0, 0, 0, 297.213, 29721.3],
      [2114630.5, 1249226, 3100, 1249226, 248, 293566, 7.96800, 7.41693, 4.95262, 6.17743, 6.9, 6.21119, 11.288, 13.8055, 13.1121, 107.468, 13685.5, 428131, 485150, 14623.1, 4.12495, 107.7, 1236760366, 0, 0, 0, 0, 297.213, 29721.3],
      [2115630.5, 1249226, 3099, 1249226, 249, 293567, 7.55300, 7.36585, 5.01813, 6.05697, 6.9, 6.21374, 11.288, 16.3858, 12.7660, 107.470, 13685.5, 428131, 485150, 14623.1, 4.12496, 107.7, 1236760367, 0, 0, 0, 0, 297.214, 29721.4],
      [2116630.5, 1249226, 3099, 1249226, 250, 293568, 8.79800, 7.42331, 7.00002, 5.99525, 6.9, 6.21374, 11.288,  9.4913, 11.5587, 107.469, 13685.5, 428131, 485150, 14623.1, 4.12495, 107.7, 1236760368, 0, 0, 0, 0, 297.215, 29721.5],
      [2117630.5, 1249226, 3099, 1249226, 251, 293569, 6.22500, 7.41134, 7.00002, 6.07219, 6.9, 6.22137, 11.288,  8.6241, 10.8684, 107.470, 13685.5, 428131, 485150, 14623.2, 4.12496, 107.7, 1236760369, 0, 0, 0, 0, 297.213, 29721.3],
      [2118630.5, 1249226, 3099, 1249226, 252, 293570, 7.47000, 7.48157, 7.00002, 6.19109, 6.9, 6.21628, 11.288,  9.4865, 10.8700, 107.470, 13685.5, 428131, 485150, 14623.2, 4.12496, 107.7, 1236760370, 0, 0, 0, 0, 297.213, 29721.3],
      [2119630.5, 1249226, 3100, 1249226, 253, 293571, 7.71900, 7.44965, 7.00002, 6.42330, 6.9, 6.21628, 11.288, 10.3541, 11.5590, 107.468, 13685.5, 428131, 485150, 14623.2, 4.12495, 107.7, 1236760371, 0, 0, 0, 0, 297.212, 29721.2],
      [2120630.5, 1249226, 3099, 1249226, 254, 293572, 7.63600, 7.56457, 6.11195, 6.66054, 6.9, 6.21119, 11.288, 16.3941, 11.5599, 107.469, 13685.5, 428131, 485150, 14623.2, 4.12496, 107.7, 1236760372, 0, 0, 0, 0, 297.212, 29721.2],
      [2121630.5, 1249226, 3100, 1249226, 255, 293573, 7.30400, 7.48796, 6.11195, 6.89779, 6.9, 6.21374, 11.288, 12.9362, 11.9261, 107.470, 13685.5, 428131, 485150, 14623.2, 4.12496, 107.7, 1236760373, 0, 0, 0, 0, 297.212, 29721.2],
      [2122630.5, 1249226, 3100, 1249226, 256, 293574, 7.13800, 7.43050, 6.14887, 7.09659, 6.9, 6.21882, 11.288,  8.6285, 11.9261, 107.469, 13685.5, 428131, 485151, 14623.2, 4.12495, 107.7, 1236760374, 0, 0, 0, 0, 297.210, 29721.0],
      [2123630.5, 1249226, 3099, 1249226, 257, 293575, 7.70344, 7.35388, 7.08488, 7.08081, 6.9, 6.21358, 11.288, 11.3174, 10.7170, 107.470, 13685.4, 428131, 485151, 14623.2, 4.12496, 107.7, 1236760375, 0, 0, 0, 0, 297.209, 29720.9],
      [2124630.5, 1249226, 3099, 1249226, 258, 293576, 7.30400, 7.46880, 7.08488, 7.00211, 6.9, 6.22391, 11.288, 10.3541, 10.7183, 107.471, 13685.4, 428131, 485151, 14623.2, 4.12497, 107.7, 1236760376, 0, 0, 0, 0, 297.209, 29720.9],
      [2125630.5, 1249226, 3097, 1249226, 259, 293577, 6.72300, 7.42411, 8.03683, 6.92341, 6.9, 6.21374, 11.288, 10.3489, 11.7524, 107.470, 13685.5, 428131, 485151, 14623.2, 4.12497, 107.7, 1236760377, 0, 0, 0, 0, 297.210, 29721.0],
      [2126630.5, 1249226, 3099, 1249226, 260, 293578, 8.79800, 7.37942, 8.03683, 6.84470, 6.9, 6.22391, 11.288, 12.9427, 11.9048, 107.470, 13685.5, 428131, 485151, 14623.2, 4.12497, 107.7, 1236760378, 0, 0, 0, 0, 297.211, 29721.1],
      [2127630.5, 1249226, 3100, 1249226, 261, 293579, 6.97200, 7.43688, 8.03683, 6.83509, 6.9, 6.21882, 11.288, 13.7986, 12.0763, 107.469, 13685.5, 428131, 485151, 14623.2, 4.12496, 107.7, 1236760379, 0, 0, 0, 0, 297.210, 29721.0],
      [2128630.5, 1249226, 3099, 1249226, 262, 293580, 6.80600, 7.39857, 7.60259, 6.82547, 6.9, 6.21882, 11.288, 12.0798, 12.5950, 107.469, 13685.4, 428131, 485151, 14623.2, 4.12495, 107.7, 1236760380, 0, 0, 0, 0, 297.207, 29720.7],
      [2129630.5, 1249226, 3097, 1249226, 263, 293581, 7.80200, 7.40496, 6.79486, 6.95780, 6.9, 6.21119, 11.288, 11.2114, 12.2488, 107.470, 13685.4, 428131, 485151, 14623.2, 4.12497, 107.7, 1236760381, 0, 0, 0, 0, 297.208, 29720.8],
      [2130630.5, 1249226, 3099, 1249226, 264, 293582, 7.71900, 7.29722, 5.97688, 7.01813, 6.9, 6.21882, 11.288, 12.9427, 11.9050, 107.470, 13685.4, 428131, 485151, 14623.2, 4.12496, 107.7, 1236760382, 0, 0, 0, 0, 297.209, 29720.9],
      [2131630.5, 1249226, 3100, 1249226, 265, 293583, 6.88900, 7.33552, 5.97688, 7.07845, 6.9, 6.21882, 11.288, 11.2114, 12.5937, 107.470, 13685.4, 428132, 485151, 14623.2, 4.12496, 107.7, 1236760383, 0, 0, 0, 0, 297.208, 29720.8],
      [2132630.5, 1249226, 3099, 1249226, 266, 293584, 7.13800, 7.40576, 5.97688, 6.96699, 6.9, 6.21628, 11.288, 12.0798, 12.4223, 107.470, 13685.4, 428132, 485151, 14623.2, 4.12496, 107.7, 1236760384, 0, 0, 0, 0, 297.207, 29720.7],
      [2133630.5, 1249226, 3097, 1249226, 267, 293585, 8.38300, 7.19506, 5.98696, 6.82008, 6.9, 6.21119, 11.288, 15.5234, 12.7660, 107.469, 13685.4, 428132, 485151, 14623.2, 4.12496, 107.7, 1236760385, 0, 0, 0, 0, 297.207, 29720.7],
      [2134630.5, 1249226, 3097, 1249226, 268, 293586, 6.80600, 7.15037, 5.98696, 6.65435, 6.9, 6.21882, 11.288, 10.3541, 13.2735, 107.469, 13685.4, 428132, 485151, 14623.2, 4.12495, 107.7, 1236760386, 0, 0, 0, 0, 297.208, 29720.8],
      [2135630.5, 1249226, 3099, 1249226, 269, 293587, 7.22100, 7.16952, 7.86912, 6.48392, 6.9, 6.21628, 11.288, 14.6610, 13.2723, 107.469, 13685.4, 428132, 485151, 14623.2, 4.12495, 107.7, 1236760387, 0, 0, 0, 0, 297.209, 29720.9],
      [2136630.5, 1249226, 3099, 1249226, 270, 293588, 6.30281, 7.08652, 7.86912, 6.32772, 6.9, 6.21835, 11.288, 13.7490, 12.7561, 107.468, 13685.4, 428132, 485151, 14623.2, 4.12495, 107.7, 1236760388, 0, 0, 0, 0, 297.208, 29720.8],
      [2137630.5, 1249226, 3099, 1249226, 271, 293589, 7.80200, 7.13122, 7.86912, 6.19430, 6.9, 6.21119, 11.288, 12.0738, 12.5826, 107.468, 13685.4, 428132, 485151, 14623.2, 4.12494, 107.7, 1236760389, 0, 0, 0, 0, 297.207, 29720.8],
      [2138630.5, 1249226, 3099, 1249226, 272, 293590, 7.63600, 7.19506, 6.58783, 6.10102, 6.9, 6.21628, 11.288, 12.9427, 11.7212, 107.468, 13685.4, 428132, 485151, 14623.2, 4.12495, 107.7, 1236760390, 0, 0, 0, 0, 297.207, 29720.7],
      [2139630.5, 1249226, 3097, 1249226, 273, 293591, 6.05900, 7.20145, 6.12695, 6.00774, 6.9, 6.21374, 11.288,  9.4865, 11.3862, 107.469, 13685.4, 428132, 485151, 14623.2, 4.12495, 107.7, 1236760391, 0, 0, 0, 0, 297.206, 29720.6],
      [2140630.5, 1249226, 3097, 1249226, 274, 293592, 6.39100, 7.12483, 5.88238, 5.95080, 6.9, 6.21374, 11.288, 10.3541, 11.3874, 107.469, 13685.4, 428132, 485151, 14623.2, 4.12495, 107.7, 1236760392, 0, 0, 0, 0, 297.206, 29720.6],
      [2141630.5, 1249226, 3100, 1249226, 275, 293593, 7.05500, 7.16952, 5.38699, 6.00525, 6.9, 6.21882, 11.288, 12.0738, 10.6962, 107.469, 13685.4, 428132, 485151, 14623.2, 4.12495, 107.7, 1236760393, 0, 0, 0, 0, 297.206, 29720.6],
      [2142630.5, 1249226, 3099, 1249226, 276, 293594, 6.72300, 7.18269, 4.76425, 5.91493, 6.9, 6.21374, 11.288, 12.0798, 11.0423, 107.470, 13685.4, 428132, 485151, 14623.2, 4.12496, 107.7, 1236760394, 0, 0, 0, 0, 297.206, 29720.6],
      [2143630.5, 1249226, 3099, 1249226, 277, 293595, 8.30000, 7.25971, 4.24250, 5.81479, 6.9, 6.21119, 11.288,  9.4865, 11.0412, 107.469, 13685.4, 428132, 485151, 14623.2, 4.12495, 107.7, 1236760395, 0, 0, 0, 0, 297.206, 29720.6],
      [2144630.5, 1249226, 3099, 1249226, 278, 293596, 7.71900, 7.19586, 4.76425, 5.64502, 6.9, 6.22137, 11.288, 11.2170, 11.9036, 107.470, 13685.4, 428132, 485151, 14623.2, 4.12496, 107.7, 1236760396, 0, 0, 0, 0, 297.206, 29720.6],
      [2145630.5, 1249226, 3097, 1249226, 279, 293597, 7.22100, 7.17671, 4.76425, 5.57381, 6.9, 6.21628, 11.288, 10.3489, 11.5585, 107.468, 13685.4, 428132, 485151, 14623.2, 4.12495, 107.7, 1236760397, 0, 0, 0, 0, 297.206, 29720.6],
      [2146630.5, 1249226, 3095, 1249226, 280, 293598, 7.38700, 7.36186, 5.24666, 5.53805, 6.9, 6.21374, 11.288, 16.3858, 11.2787, 107.467, 13685.4, 428132, 485151, 14623.2, 4.12494, 107.6, 1236760398, 0, 0, 0, 0, 297.205, 29720.5],
      [2147630.5, 1249226, 3097, 1249226, 281, 293599, 7.38700, 7.43848, 6.69488, 5.53645, 6.9, 6.21374, 11.288, 10.3541, 11.1051, 107.468, 13685.4, 428132, 485151, 14623.2, 4.12494, 107.6, 1236760399, 0, 0, 0, 0, 297.204, 29720.4],
      [2148630.5, 1249226, 3100, 1249226, 282, 293600, 7.39219, 7.43848, 6.69488, 5.57296, 6.9, 6.22312, 11.288,  8.0877, 11.9690, 107.469, 13685.4, 428132, 485151, 14623.2, 4.12495, 107.6, 1236760400, 0, 0, 0, 0, 297.203, 29720.3],
      [2149630.5, 1249226, 3099, 1249226, 283, 293601, 7.30400, 7.45125, 6.56732, 5.70405, 6.9, 6.21374, 11.288, 10.3489, 10.2442, 107.468, 13685.4, 428132, 485151, 14623.2, 4.12494, 107.6, 1236760401, 0, 0, 0, 0, 297.204, 29720.4],
      [2150630.5, 1249226, 3097, 1249226, 284, 293602, 6.97200, 7.38101, 5.66211, 5.91139, 6.9, 6.22137, 11.288, 14.6684,  9.5539, 107.468, 13685.4, 428132, 485151, 14623.2, 4.12494, 107.6, 1236760402, 0, 0, 0, 0, 297.205, 29720.5],
      [2151630.5, 1249226, 3097, 1249226, 285, 293603, 7.38700, 7.38101, 5.66211, 6.07860, 6.9, 6.21374, 11.288,  7.7617, 10.0062, 107.469, 13685.4, 428132, 485152, 14623.2, 4.12495, 107.6, 1236760403, 0, 0, 0, 0, 297.205, 29720.5],
      [2152630.5, 1249226, 3100, 1249226, 286, 293604, 8.46600, 7.42571, 5.66211, 6.30019, 6.9, 6.22137, 11.288,  6.9028, 10.3511, 107.469, 13685.4, 428132, 485152, 14623.2, 4.12495, 107.6, 1236760404, 0, 0, 0, 0, 297.204, 29720.4],
      [2153630.5, 1249226, 3097, 1249226, 287, 293605, 7.38700, 7.38101, 5.86161, 6.48467, 6.9, 6.21119, 11.288, 10.3489, 10.8688, 107.468, 13685.4, 428132, 485152, 14623.2, 4.12494, 107.6, 1236760405, 0, 0, 0, 0, 297.203, 29720.3],
      [2154630.5, 1249226, 3097, 1249226, 288, 293606, 7.05500, 7.42571, 5.86161, 6.55775, 6.9, 6.21374, 11.288, 12.0738, 11.5588, 107.467, 13685.4, 428132, 485152, 14623.2, 4.12494, 107.6, 1236760406, 0, 0, 0, 0, 297.203, 29720.3],
      [2155630.5, 1249226, 3099, 1249226, 289, 293607, 6.88900, 7.43169, 6.46834, 6.63850, 6.9, 6.21119, 11.288, 17.2569, 11.9039, 107.467, 13685.4, 428132, 485152, 14623.2, 4.12494, 107.6, 1236760407, 0, 0, 0, 0, 297.204, 29720.4],
      [2156630.5, 1249226, 3099, 1249226, 290, 293608, 7.38700, 7.47639, 6.93797, 6.69372, 6.9, 6.21882, 11.288, 11.2114, 11.7314, 107.468, 13685.4, 428132, 485152, 14623.2, 4.12494, 107.6, 1236760408, 0, 0, 0, 0, 297.204, 29720.4],
      [2157630.5, 1249226, 3097, 1249226, 291, 293609, 7.71900, 7.49554, 6.93797, 6.75318, 6.9, 6.21119, 11.288,  8.6285, 11.9052, 107.469, 13685.3, 428132, 485152, 14623.2, 4.12495, 107.6, 1236760409, 0, 0, 0, 0, 297.202, 29720.2],
      [2158630.5, 1249226, 3095, 1249226, 292, 293610, 7.80200, 7.52108, 7.64489, 6.81264, 6.9, 6.21374, 11.288,  9.4865, 10.0062, 107.468, 13685.3, 428132, 485152, 14623.2, 4.12494, 107.6, 1236760410, 0, 0, 0, 0, 297.202, 29720.2],
      [2159630.5, 1249226, 3095, 1249226, 293, 293611, 6.80600, 7.43808, 7.64489, 6.97818, 6.9, 6.21374, 11.288, 12.9427, 10.9989, 107.468, 13685.4, 428132, 485152, 14623.2, 4.12494, 107.6, 1236760411, 0, 0, 0, 0, 297.203, 29720.3],
      [2160630.5, 1249226, 3097, 1249226, 294, 293612, 7.96800, 7.43169, 7.64489, 7.10750, 6.9, 6.21628, 11.288,  7.7617, 11.1715, 107.468, 13685.4, 428132, 485152, 14623.2, 4.12495, 107.6, 1236760412, 0, 0, 0, 0, 297.202, 29720.2],
      [2161630.5, 1249226, 3097, 1249226, 295, 293613, 7.47000, 7.38061, 7.74472, 7.23681, 6.9, 6.21596, 11.288, 16.1753, 11.1715, 107.469, 13685.3, 428132, 485152, 14623.2, 4.12495, 107.6, 1236760413, 0, 0, 0, 0, 297.202, 29720.2],
      [2162630.5, 1249226, 3097, 1249226, 296, 293614, 7.88500, 7.36785, 7.28508, 7.31946, 6.9, 6.21628, 11.288,  9.4913, 10.1353, 107.468, 13685.3, 428133, 485152, 14623.2, 4.12495, 107.6, 1236760414, 0, 0, 0, 0, 297.201, 29720.1],
      [2163630.5, 1249226, 3097, 1249226, 297, 293615, 7.22100, 7.40615, 6.43515, 7.20939, 6.9, 6.21119, 11.288,  9.4865, 10.1361, 107.468, 13685.3, 428133, 485152, 14623.2, 4.12495, 107.6, 1236760415, 0, 0, 0, 0, 297.201, 29720.1],
      [2164630.5, 1249226, 3097, 1249226, 298, 293616, 7.71900, 7.32315, 6.43515, 7.09933, 6.9, 6.21374, 11.288,  7.7617, 10.1782, 107.470, 13685.3, 428133, 485152, 14623.2, 4.12496, 107.6, 1236760416, 0, 0, 0, 0, 297.201, 29720.1],
      [2165630.5, 1249226, 3099, 1249226, 299, 293617, 7.38700, 7.34231, 7.81408, 6.93488, 6.9, 6.21628, 11.288,  7.7656, 11.5588, 107.467, 13685.3, 428133, 485152, 14623.2, 4.12494, 107.6, 1236760417, 0, 0, 0, 0, 297.202, 29720.2],
      [2166630.5, 1249226, 3099, 1249226, 300, 293618, 7.30400, 7.36785, 7.54272, 6.79481, 6.9, 6.21374, 11.288, 16.3858, 11.5588, 107.469, 13685.3, 428133, 485152, 14623.2, 4.12495, 107.6, 1236760418, 0, 0, 0, 0, 297.201, 29720.1],
      [2167630.5, 1249226, 3097, 1249226, 301, 293619, 6.39100, 7.31677, 7.54272, 6.70996, 6.9, 6.21119, 11.288, 16.3941, 12.0772, 107.469, 13685.3, 428133, 485152, 14623.2, 4.12495, 107.6, 1236760419, 0, 0, 0, 0, 297.200, 29720.0],
      [2168630.5, 1249226, 3095, 1249226, 302, 293620, 6.72300, 7.22699, 7.54272, 6.72068, 6.9, 6.21628, 11.288,  9.4865, 12.5939, 107.467, 13685.3, 428133, 485152, 14623.2, 4.12494, 107.6, 1236760420, 0, 0, 0, 0, 297.201, 29720.1],
      [2169630.5, 1249226, 3099, 1249226, 303, 293621, 7.88500, 7.23337, 5.50712, 6.76676, 6.9, 6.21628, 11.288, 10.3541, 11.5601, 107.467, 13685.3, 428133, 485152, 14623.2, 4.12493, 107.6, 1236760421, 0, 0, 0, 0, 297.201, 29720.1],
      [2170630.5, 1249226, 3097, 1249226, 304, 293622, 6.64000, 7.27168, 5.50712, 6.80439, 6.9, 6.21882, 11.288, 10.3489, 10.0062, 107.467, 13685.3, 428133, 485152, 14623.2, 4.12494, 107.6, 1236760422, 0, 0, 0, 0, 297.199, 29719.9],
      [2171630.5, 1249226, 3099, 1249226, 305, 293623, 8.05100, 7.25252, 5.50712, 6.84201, 6.9, 6.21628, 11.288, 11.2170, 11.3860, 107.468, 13685.3, 428133, 485152, 14623.2, 4.12494, 107.6, 1236760423, 0, 0, 0, 0, 297.199, 29719.9],
      [2172630.5, 1249226, 3095, 1249226, 306, 293624, 7.13800, 7.10568, 5.82392, 6.71847, 6.9, 6.21374, 11.288,  8.6241, 12.5502, 107.467, 13685.3, 428133, 485152, 14623.2, 4.12493, 107.6, 1236760424, 0, 0, 0, 0, 297.199, 29719.9],
      [2173630.5, 1249226, 3097, 1249226, 307, 293625, 7.30400, 7.12483, 6.54191, 6.61580, 6.9, 6.21119, 11.288, 16.3858, 12.5513, 107.467, 13685.3, 428133, 485152, 14623.2, 4.12493, 107.6, 1236760425, 0, 0, 0, 0, 297.200, 29720.0],
      [2174630.5, 1249226, 3095, 1249226, 308, 293626, 6.30281, 7.27168, 7.88407, 6.51313, 6.9, 6.21358, 11.288, 16.1753, 13.0662, 107.466, 13685.3, 428133, 485152, 14623.2, 4.12493, 107.6, 1236760426, 0, 0, 0, 0, 297.200, 29720.0],
      [2175630.5, 1249226, 3095, 1249226, 309, 293627, 7.96800, 7.29083, 7.88407, 6.45446, 6.9, 6.21882, 11.288, 10.3541, 12.7226, 107.467, 13685.3, 428133, 485152, 14623.2, 4.12493, 107.6, 1236760427, 0, 0, 0, 0, 297.200, 29720.0],
      [2176630.5, 1249226, 3097, 1249226, 310, 293628, 7.71900, 7.25891, 6.92433, 6.56699, 6.9, 6.21374, 11.288, 13.7917, 11.5153, 107.465, 13685.3, 428133, 485152, 14623.2, 4.12492, 107.6, 1236760428, 0, 0, 0, 0, 297.200, 29720.0],
      [2177630.5, 1249226, 3095, 1249226, 311, 293629, 7.47000, 7.37383, 6.92433, 6.67951, 6.9, 6.21119, 11.288,  6.9062, 10.1785, 107.466, 13685.3, 428133, 485152, 14623.2, 4.12493, 107.6, 1236760429, 0, 0, 0, 0, 297.200, 29720.0],
      [2178630.5, 1249226, 3095, 1249226, 312, 293630, 5.47800, 7.32914, 6.20800, 6.82894, 6.9, 6.21374, 11.288, 10.3489, 10.0049, 107.466, 13685.3, 428133, 485152, 14623.2, 4.12493, 107.6, 1236760430, 0, 0, 0, 0, 297.198, 29719.8],
      [2179630.5, 1249226, 3095, 1249226, 313, 293631, 7.55300, 7.39299, 6.20800, 6.96524, 6.9, 6.21374, 11.288,  9.4913, 10.5254, 107.466, 13685.3, 428133, 485152, 14623.2, 4.12492, 107.6, 1236760431, 0, 0, 0, 0, 297.199, 29719.9],
      [2180630.5, 1249226, 3094, 1249226, 314, 293632, 8.30000, 7.38181, 6.20800, 7.03508, 6.9, 6.21374, 11.288,  9.4865, 11.9039, 107.468, 13685.3, 428133, 485152, 14623.2, 4.12495, 107.6, 1236760432, 0, 0, 0, 0, 297.199, 29719.9],
      [2181630.5, 1249226, 3097, 1249226, 315, 293633, 6.97200, 7.49075, 6.78007, 6.96766, 6.9, 6.21374, 11.288, 16.3941, 11.7324, 107.466, 13685.3, 428133, 485152, 14623.2, 4.12493, 107.6, 1236760433, 0, 0, 0, 0, 297.199, 29719.9],
      [2182630.5, 1249226, 3097, 1249226, 316, 293634, 7.47000, 7.46521, 6.96991, 6.90434, 6.9, 6.21374, 11.288, 13.7986, 12.0764, 107.466, 13685.3, 428133, 485152, 14623.2, 4.12493, 107.6, 1236760434, 0, 0, 0, 0, 297.199, 29719.9],
      [2183630.5, 1249226, 3095, 1249226, 317, 293635, 8.13400, 7.39498, 6.96991, 6.91485, 6.9, 6.21374, 11.288,  9.4913, 11.5596, 107.467, 13685.3, 428133, 485153, 14623.2, 4.12494, 107.6, 1236760435, 0, 0, 0, 0, 297.197, 29719.7],
      [2184630.5, 1249226, 3095, 1249226, 318, 293636, 7.47000, 7.40136, 7.44978, 6.92536, 6.9, 6.21628, 11.288, 11.2114, 11.5143, 107.466, 13685.3, 428133, 485153, 14623.2, 4.12493, 107.6, 1236760436, 0, 0, 0, 0, 297.197, 29719.7],
      [2185630.5, 1249226, 3095, 1249226, 319, 293637, 7.96800, 7.56098, 7.59581, 6.99098, 6.9, 6.22137, 11.288,  6.9028, 10.4803, 107.466, 13685.3, 428133, 485153, 14623.2, 4.12493, 107.6, 1236760437, 0, 0, 0, 0, 297.197, 29719.7],
      [2186630.5, 1249226, 3097, 1249226, 320, 293638, 7.15875, 7.56098, 7.44978, 7.05659, 6.9, 6.21358, 11.288, 16.1677, 11.3404, 107.468, 13685.3, 428133, 485153, 14623.2, 4.12494, 107.6, 1236760438, 0, 0, 0, 0, 297.198, 29719.8],
      [2187630.5, 1249226, 3095, 1249226, 321, 293639, 7.71900, 7.50352, 7.00762, 7.12220, 6.9, 6.22137, 11.288,  8.6285, 13.2419, 107.467, 13685.3, 428133, 485153, 14623.2, 4.12494, 107.6, 1236760439, 0, 0, 0, 0, 297.197, 29719.7],
      [2188630.5, 1249226, 3095, 1249226, 322, 293640, 7.63600, 7.54821, 7.06095, 7.14381, 6.9, 6.21628, 11.288, 13.7917, 13.0687, 107.466, 13685.3, 428133, 485153, 14623.2, 4.12493, 107.6, 1236760440, 0, 0, 0, 0, 297.196, 29719.6],
      [2189630.5, 1249226, 3095, 1249226, 323, 293641, 6.80600, 7.55460, 7.06095, 7.15081, 6.9, 6.21119, 11.288, 20.7187, 13.0687, 107.466, 13685.3, 428133, 485153, 14623.2, 4.12492, 107.6, 1236760441, 0, 0, 0, 0, 297.196, 29719.6],
      [2190630.5, 1249226, 3095, 1249226, 324, 293642, 7.55300, 7.50990, 7.06095, 7.15781, 6.9, 6.21628, 11.288,  6.0369, 13.0687, 107.465, 13685.3, 428133, 485153, 14623.2, 4.12492, 107.6, 1236760442, 0, 0, 0, 0, 297.197, 29719.6]
    ]
  }
]
